[[{"d_time": 145, "time": 79920, "latitude": 37.737725, "route": "35", "trip": " 8514", "longitude": -122.429531, "size": 0}, {"route": "35", "longitude": -122.429531, "d_time": 145, "time": 79920, "latitude": 37.737725, "trip": " 8514", "size": 10}, {"route": "35", "longitude": -122.435476, "d_time": 145, "time": 79200, "latitude": 37.74192, "trip": " 8514", "size": 10}, {"route": "35", "longitude": -122.435476, "d_time": 159, "time": 79680, "latitude": 37.74192, "trip": " 8514", "size": 10}, {"route": "35", "longitude": -122.429531, "d_time": 109, "time": 81720, "latitude": 37.737725, "trip": " 8514", "size": 10}, {"route": "35", "longitude": -122.435476, "d_time": 109, "time": 81000, "latitude": 37.74192, "trip": " 8514", "size": 10}, {"route": "35", "longitude": -122.435476, "d_time": 138, "time": 81480, "latitude": 37.74192, "trip": " 8514", "size": 10}, {"route": "35", "longitude": -122.429531, "d_time": 172, "time": 83520, "latitude": 37.737725, "trip": " 8514", "size": 10}, {"route": "35", "longitude": -122.435476, "d_time": 172, "time": 82800, "latitude": 37.74192, "trip": " 8514", "size": 10}, {"route": "35", "longitude": -122.435476, "d_time": 222, "time": 83280, "latitude": 37.74192, "trip": " 8514", "size": 10}, {"d_time": 222, "time": 83880, "latitude": 37.74192, "route": "35", "trip": " 8514", "longitude": -122.435476, "size": 0}], [{"d_time": 109, "time": 78120, "latitude": 37.737725, "route": "35", "trip": " 8514", "longitude": -122.429531, "size": 0}, {"route": "35", "longitude": -122.429531, "d_time": 109, "time": 78120, "latitude": 37.737725, "trip": " 8514", "size": 10}, {"route": "35", "longitude": -122.435476, "d_time": 109, "time": 77400, "latitude": 37.74192, "trip": " 8514", "size": 10}, {"route": "35", "longitude": -122.435476, "d_time": 131, "time": 77880, "latitude": 37.74192, "trip": " 8514", "size": 10}, {"route": "35", "longitude": -122.429531, "d_time": 62, "time": 76380, "latitude": 37.737725, "trip": " 8514", "size": 10}, {"route": "35", "longitude": -122.435476, "d_time": 62, "time": 75600, "latitude": 37.74192, "trip": " 8514", "size": 10}, {"route": "35", "longitude": -122.435476, "d_time": 151, "time": 76140, "latitude": 37.74192, "trip": " 8514", "size": 10}, {"route": "35", "longitude": -122.429531, "d_time": 39, "time": 74580, "latitude": 37.737725, "trip": " 8514", "size": 10}, {"route": "35", "longitude": -122.435476, "d_time": 39, "time": 73800, "latitude": 37.74192, "trip": " 8514", "size": 10}, {"route": "35", "longitude": -122.435476, "d_time": 99, "time": 74340, "latitude": 37.74192, "trip": " 8514", "size": 10}, {"route": "35", "longitude": -122.429531, "d_time": 39, "time": 72780, "latitude": 37.737725, "trip": " 8514", "size": 10}, {"route": "35", "longitude": -122.435476, "d_time": 39, "time": 72000, "latitude": 37.74192, "trip": " 8514", "size": 10}, {"route": "35", "longitude": -122.435476, "d_time": 109, "time": 72540, "latitude": 37.74192, "trip": " 8514", "size": 10}, {"route": "35", "longitude": -122.429531, "d_time": 38, "time": 70980, "latitude": 37.737725, "trip": " 8514", "size": 10}, {"route": "35", "longitude": -122.435476, "d_time": 38, "time": 70200, "latitude": 37.74192, "trip": " 8514", "size": 10}, {"route": "35", "longitude": -122.435476, "d_time": 73, "time": 70740, "latitude": 37.74192, "trip": " 8514", "size": 10}, {"route": "35", "longitude": -122.429531, "d_time": 189, "time": 69180, "latitude": 37.737725, "trip": " 8514", "size": 10}, {"route": "35", "longitude": -122.435476, "d_time": 189, "time": 68400, "latitude": 37.74192, "trip": " 8514", "size": 10}, {"route": "35", "longitude": -122.435476, "d_time": 179, "time": 68940, "latitude": 37.74192, "trip": " 8514", "size": 10}, {"route": "35", "longitude": -122.429531, "d_time": 128, "time": 67380, "latitude": 37.737725, "trip": " 8514", "size": 10}, {"route": "35", "longitude": -122.435476, "d_time": 128, "time": 66600, "latitude": 37.74192, "trip": " 8514", "size": 10}, {"route": "35", "longitude": -122.435476, "d_time": 188, "time": 67140, "latitude": 37.74192, "trip": " 8514", "size": 10}, {"route": "35", "longitude": -122.429531, "d_time": 262, "time": 65580, "latitude": 37.737725, "trip": " 8514", "size": 10}, {"route": "35", "longitude": -122.435476, "d_time": 262, "time": 64800, "latitude": 37.74192, "trip": " 8514", "size": 10}, {"route": "35", "longitude": -122.435476, "d_time": 228, "time": 65340, "latitude": 37.74192, "trip": " 8514", "size": 10}, {"route": "35", "longitude": -122.429531, "d_time": 194, "time": 63780, "latitude": 37.737725, "trip": " 8514", "size": 10}, {"route": "35", "longitude": -122.435476, "d_time": 194, "time": 63000, "latitude": 37.74192, "trip": " 8514", "size": 10}, {"route": "35", "longitude": -122.435476, "d_time": 210, "time": 63540, "latitude": 37.74192, "trip": " 8514", "size": 10}, {"route": "35", "longitude": -122.429531, "d_time": 208, "time": 61980, "latitude": 37.737725, "trip": " 8514", "size": 10}, {"route": "35", "longitude": -122.435476, "d_time": 208, "time": 61200, "latitude": 37.74192, "trip": " 8514", "size": 10}, {"route": "35", "longitude": -122.435476, "d_time": 224, "time": 61740, "latitude": 37.74192, "trip": " 8514", "size": 10}, {"route": "35", "longitude": -122.429531, "d_time": 170, "time": 60180, "latitude": 37.737725, "trip": " 8514", "size": 10}, {"route": "35", "longitude": -122.435476, "d_time": 170, "time": 59400, "latitude": 37.74192, "trip": " 8514", "size": 10}, {"route": "35", "longitude": -122.435476, "d_time": 134, "time": 59940, "latitude": 37.74192, "trip": " 8514", "size": 10}, {"route": "35", "longitude": -122.429531, "d_time": 259, "time": 58380, "latitude": 37.737725, "trip": " 8514", "size": 10}, {"route": "35", "longitude": -122.435476, "d_time": 259, "time": 57600, "latitude": 37.74192, "trip": " 8514", "size": 10}, {"route": "35", "longitude": -122.435476, "d_time": 275, "time": 58140, "latitude": 37.74192, "trip": " 8514", "size": 10}, {"route": "35", "longitude": -122.429531, "d_time": 677, "time": 56580, "latitude": 37.737725, "trip": " 8514", "size": 10}, {"route": "35", "longitude": -122.435476, "d_time": 677, "time": 55800, "latitude": 37.74192, "trip": " 8514", "size": 10}, {"route": "35", "longitude": -122.435476, "d_time": 661, "time": 56340, "latitude": 37.74192, "trip": " 8514", "size": 10}, {"d_time": 661, "time": 56940, "latitude": 37.74192, "route": "35", "trip": " 8514", "longitude": -122.435476, "size": 0}], [{"d_time": 0, "time": 54780, "latitude": 37.737725, "route": "35", "trip": " 8517", "longitude": -122.429531, "size": 0}, {"route": "35", "longitude": -122.429531, "d_time": 0, "time": 54780, "latitude": 37.737725, "trip": " 8517", "size": 10}, {"route": "35", "longitude": -122.429531, "d_time": 0, "time": 54000, "latitude": 37.737725, "trip": " 8517", "size": 10}, {"route": "35", "longitude": -122.429531, "d_time": 0, "time": 54540, "latitude": 37.737725, "trip": " 8517", "size": 10}, {"route": "35", "longitude": -122.429531, "d_time": 356, "time": 52920, "latitude": 37.737725, "trip": " 8517", "size": 10}, {"route": "35", "longitude": -122.435476, "d_time": 356, "time": 52200, "latitude": 37.74192, "trip": " 8517", "size": 10}, {"route": "35", "longitude": -122.435476, "d_time": 191, "time": 52740, "latitude": 37.74192, "trip": " 8517", "size": 10}, {"route": "35", "longitude": -122.429531, "d_time": 172, "time": 51120, "latitude": 37.737725, "trip": " 8517", "size": 10}, {"route": "35", "longitude": -122.435476, "d_time": 172, "time": 50400, "latitude": 37.74192, "trip": " 8517", "size": 10}, {"route": "35", "longitude": -122.435476, "d_time": 159, "time": 50940, "latitude": 37.74192, "trip": " 8517", "size": 10}, {"route": "35", "longitude": -122.429531, "d_time": -9, "time": 49320, "latitude": 37.737725, "trip": " 8517", "size": 10}, {"route": "35", "longitude": -122.435476, "d_time": -9, "time": 48600, "latitude": 37.74192, "trip": " 8517", "size": 10}, {"route": "35", "longitude": -122.435476, "d_time": -38, "time": 49140, "latitude": 37.74192, "trip": " 8517", "size": 10}, {"route": "35", "longitude": -122.429531, "d_time": 88, "time": 47520, "latitude": 37.737725, "trip": " 8517", "size": 10}, {"route": "35", "longitude": -122.435476, "d_time": 88, "time": 46800, "latitude": 37.74192, "trip": " 8517", "size": 10}, {"route": "35", "longitude": -122.435476, "d_time": 23, "time": 47340, "latitude": 37.74192, "trip": " 8517", "size": 10}, {"d_time": 23, "time": 47940, "latitude": 37.74192, "route": "35", "trip": " 8517", "longitude": -122.435476, "size": 0}], [{"d_time": 173, "time": 88920, "latitude": 37.737725, "route": "35", "trip": " 8517", "longitude": -122.429531, "size": 0}, {"route": "35", "longitude": -122.429531, "d_time": 173, "time": 88920, "latitude": 37.737725, "trip": " 8517", "size": 10}, {"route": "35", "longitude": -122.435476, "d_time": 173, "time": 88200, "latitude": 37.74192, "trip": " 8517", "size": 10}, {"route": "35", "longitude": -122.435476, "d_time": 121, "time": 88740, "latitude": 37.74192, "trip": " 8517", "size": 10}, {"route": "35", "longitude": -122.429531, "d_time": 0, "time": 87120, "latitude": 37.737725, "trip": " 8517", "size": 10}, {"route": "35", "longitude": -122.429531, "d_time": 0, "time": 86400, "latitude": 37.737725, "trip": " 8517", "size": 10}, {"route": "35", "longitude": -122.429531, "d_time": 0, "time": 86940, "latitude": 37.737725, "trip": " 8517", "size": 10}, {"d_time": 0, "time": 87540, "latitude": 37.737725, "route": "35", "trip": " 8517", "longitude": -122.429531, "size": 0}], [{"d_time": 59, "time": 42120, "latitude": 37.737725, "route": "35", "trip": " 8517", "longitude": -122.429531, "size": 0}, {"route": "35", "longitude": -122.429531, "d_time": 59, "time": 42120, "latitude": 37.737725, "trip": " 8517", "size": 10}, {"route": "35", "longitude": -122.435476, "d_time": 59, "time": 41400, "latitude": 37.74192, "trip": " 8517", "size": 10}, {"route": "35", "longitude": -122.435476, "d_time": 35, "time": 41940, "latitude": 37.74192, "trip": " 8517", "size": 10}, {"route": "35", "longitude": -122.429531, "d_time": 185, "time": 40260, "latitude": 37.737725, "trip": " 8517", "size": 10}, {"route": "35", "longitude": -122.435476, "d_time": 185, "time": 39600, "latitude": 37.74192, "trip": " 8517", "size": 10}, {"route": "35", "longitude": -122.435476, "d_time": 123, "time": 40080, "latitude": 37.74192, "trip": " 8517", "size": 10}, {"route": "35", "longitude": -122.429531, "d_time": 199, "time": 38460, "latitude": 37.737725, "trip": " 8517", "size": 10}, {"route": "35", "longitude": -122.435476, "d_time": 199, "time": 37800, "latitude": 37.74192, "trip": " 8517", "size": 10}, {"route": "35", "longitude": -122.435476, "d_time": 187, "time": 38280, "latitude": 37.74192, "trip": " 8517", "size": 10}, {"route": "35", "longitude": -122.429531, "d_time": 164, "time": 36660, "latitude": 37.737725, "trip": " 8517", "size": 10}, {"route": "35", "longitude": -122.435476, "d_time": 164, "time": 36000, "latitude": 37.74192, "trip": " 8517", "size": 10}, {"route": "35", "longitude": -122.435476, "d_time": 140, "time": 36480, "latitude": 37.74192, "trip": " 8517", "size": 10}, {"route": "35", "longitude": -122.429531, "d_time": 131, "time": 34860, "latitude": 37.737725, "trip": " 8517", "size": 10}, {"route": "35", "longitude": -122.435476, "d_time": 131, "time": 34200, "latitude": 37.74192, "trip": " 8517", "size": 10}, {"route": "35", "longitude": -122.435476, "d_time": 111, "time": 34680, "latitude": 37.74192, "trip": " 8517", "size": 10}, {"route": "35", "longitude": -122.429531, "d_time": 102, "time": 33060, "latitude": 37.737725, "trip": " 8517", "size": 10}, {"route": "35", "longitude": -122.435476, "d_time": 102, "time": 32400, "latitude": 37.74192, "trip": " 8517", "size": 10}, {"route": "35", "longitude": -122.435476, "d_time": 34, "time": 32880, "latitude": 37.74192, "trip": " 8517", "size": 10}, {"route": "35", "longitude": -122.429531, "d_time": 81, "time": 31320, "latitude": 37.737725, "trip": " 8517", "size": 10}, {"route": "35", "longitude": -122.435476, "d_time": 81, "time": 30600, "latitude": 37.74192, "trip": " 8517", "size": 10}, {"route": "35", "longitude": -122.435476, "d_time": 97, "time": 31080, "latitude": 37.74192, "trip": " 8517", "size": 10}, {"route": "35", "longitude": -122.429531, "d_time": 85, "time": 29520, "latitude": 37.737725, "trip": " 8517", "size": 10}, {"route": "35", "longitude": -122.435476, "d_time": 85, "time": 28800, "latitude": 37.74192, "trip": " 8517", "size": 10}, {"route": "35", "longitude": -122.435476, "d_time": 148, "time": 29280, "latitude": 37.74192, "trip": " 8517", "size": 10}, {"d_time": 148, "time": 29880, "latitude": 37.74192, "route": "35", "trip": " 8517", "longitude": -122.435476, "size": 0}], [{"d_time": 140, "time": 79920, "latitude": 37.737725, "route": "35", "trip": " 8514", "longitude": -122.429531, "size": 0}, {"route": "35", "longitude": -122.429531, "d_time": 140, "time": 79920, "latitude": 37.737725, "trip": " 8514", "size": 10}, {"route": "35", "longitude": -122.435197, "d_time": 131, "time": 80580, "latitude": 37.762674, "trip": " 8514", "size": 10}, {"route": "35", "longitude": -122.43535, "d_time": 132, "time": 80100, "latitude": 37.741599, "trip": " 8514", "size": 10}, {"route": "35", "longitude": -122.429531, "d_time": 106, "time": 81720, "latitude": 37.737725, "trip": " 8514", "size": 10}, {"route": "35", "longitude": -122.435197, "d_time": 45, "time": 82380, "latitude": 37.762674, "trip": " 8514", "size": 10}, {"route": "35", "longitude": -122.43535, "d_time": 64, "time": 81900, "latitude": 37.741599, "trip": " 8514", "size": 10}, {"route": "35", "longitude": -122.429531, "d_time": 188, "time": 83520, "latitude": 37.737725, "trip": " 8514", "size": 10}, {"route": "35", "longitude": -122.43535, "d_time": 188, "time": 84180, "latitude": 37.741599, "trip": " 8514", "size": 10}, {"route": "35", "longitude": -122.43535, "d_time": 140, "time": 83700, "latitude": 37.741599, "trip": " 8514", "size": 10}, {"d_time": 140, "time": 84300, "latitude": 37.741599, "route": "35", "trip": " 8514", "longitude": -122.43535, "size": 0}], [{"d_time": 110, "time": 76380, "latitude": 37.737725, "route": "35", "trip": " 8514", "longitude": -122.429531, "size": 0}, {"route": "35", "longitude": -122.429531, "d_time": 110, "time": 76380, "latitude": 37.737725, "trip": " 8514", "size": 10}, {"route": "35", "longitude": -122.435197, "d_time": 55, "time": 77040, "latitude": 37.762674, "trip": " 8514", "size": 10}, {"route": "35", "longitude": -122.43535, "d_time": 65, "time": 76560, "latitude": 37.741599, "trip": " 8514", "size": 10}, {"route": "35", "longitude": -122.429531, "d_time": 113, "time": 78120, "latitude": 37.737725, "trip": " 8514", "size": 10}, {"route": "35", "longitude": -122.435197, "d_time": 72, "time": 78780, "latitude": 37.762674, "trip": " 8514", "size": 10}, {"route": "35", "longitude": -122.43535, "d_time": 67, "time": 78300, "latitude": 37.741599, "trip": " 8514", "size": 10}, {"d_time": 67, "time": 78900, "latitude": 37.741599, "route": "35", "trip": " 8514", "longitude": -122.43535, "size": 0}], [{"d_time": 67, "time": 74580, "latitude": 37.737725, "route": "35", "trip": " 8514", "longitude": -122.429531, "size": 0}, {"route": "35", "longitude": -122.429531, "d_time": 67, "time": 74580, "latitude": 37.737725, "trip": " 8514", "size": 10}, {"route": "35", "longitude": -122.435197, "d_time": 50, "time": 75240, "latitude": 37.762674, "trip": " 8514", "size": 10}, {"route": "35", "longitude": -122.43535, "d_time": 37, "time": 74760, "latitude": 37.741599, "trip": " 8514", "size": 10}, {"route": "35", "longitude": -122.429531, "d_time": 74, "time": 72780, "latitude": 37.737725, "trip": " 8514", "size": 10}, {"route": "35", "longitude": -122.435197, "d_time": 49, "time": 73440, "latitude": 37.762674, "trip": " 8514", "size": 10}, {"route": "35", "longitude": -122.43535, "d_time": 29, "time": 72960, "latitude": 37.741599, "trip": " 8514", "size": 10}, {"route": "35", "longitude": -122.429531, "d_time": 54, "time": 70980, "latitude": 37.737725, "trip": " 8514", "size": 10}, {"route": "35", "longitude": -122.435197, "d_time": 52, "time": 71640, "latitude": 37.762674, "trip": " 8514", "size": 10}, {"route": "35", "longitude": -122.43535, "d_time": 22, "time": 71160, "latitude": 37.741599, "trip": " 8514", "size": 10}, {"route": "35", "longitude": -122.429531, "d_time": 195, "time": 69180, "latitude": 37.737725, "trip": " 8514", "size": 10}, {"route": "35", "longitude": -122.435197, "d_time": 236, "time": 69840, "latitude": 37.762674, "trip": " 8514", "size": 10}, {"route": "35", "longitude": -122.43535, "d_time": 185, "time": 69360, "latitude": 37.741599, "trip": " 8514", "size": 10}, {"route": "35", "longitude": -122.429531, "d_time": 162, "time": 67380, "latitude": 37.737725, "trip": " 8514", "size": 10}, {"route": "35", "longitude": -122.435197, "d_time": 153, "time": 68040, "latitude": 37.762674, "trip": " 8514", "size": 10}, {"route": "35", "longitude": -122.43535, "d_time": 113, "time": 67560, "latitude": 37.741599, "trip": " 8514", "size": 10}, {"route": "35", "longitude": -122.429531, "d_time": 248, "time": 65580, "latitude": 37.737725, "trip": " 8514", "size": 10}, {"route": "35", "longitude": -122.435197, "d_time": 246, "time": 66240, "latitude": 37.762674, "trip": " 8514", "size": 10}, {"route": "35", "longitude": -122.43535, "d_time": 216, "time": 65760, "latitude": 37.741599, "trip": " 8514", "size": 10}, {"route": "35", "longitude": -122.429531, "d_time": 247, "time": 63780, "latitude": 37.737725, "trip": " 8514", "size": 10}, {"route": "35", "longitude": -122.435197, "d_time": 241, "time": 64440, "latitude": 37.762674, "trip": " 8514", "size": 10}, {"route": "35", "longitude": -122.43535, "d_time": 212, "time": 63960, "latitude": 37.741599, "trip": " 8514", "size": 10}, {"route": "35", "longitude": -122.429531, "d_time": 208, "time": 61980, "latitude": 37.737725, "trip": " 8514", "size": 10}, {"route": "35", "longitude": -122.435197, "d_time": 166, "time": 62640, "latitude": 37.762674, "trip": " 8514", "size": 10}, {"route": "35", "longitude": -122.43535, "d_time": 162, "time": 62160, "latitude": 37.741599, "trip": " 8514", "size": 10}, {"route": "35", "longitude": -122.429531, "d_time": 164, "time": 60180, "latitude": 37.737725, "trip": " 8514", "size": 10}, {"route": "35", "longitude": -122.435197, "d_time": 170, "time": 60840, "latitude": 37.762674, "trip": " 8514", "size": 10}, {"route": "35", "longitude": -122.43535, "d_time": 126, "time": 60360, "latitude": 37.741599, "trip": " 8514", "size": 10}, {"route": "35", "longitude": -122.429531, "d_time": 264, "time": 58380, "latitude": 37.737725, "trip": " 8514", "size": 10}, {"route": "35", "longitude": -122.435197, "d_time": 291, "time": 59040, "latitude": 37.762674, "trip": " 8514", "size": 10}, {"route": "35", "longitude": -122.43535, "d_time": 245, "time": 58560, "latitude": 37.741599, "trip": " 8514", "size": 10}, {"route": "35", "longitude": -122.429531, "d_time": 687, "time": 56580, "latitude": 37.737725, "trip": " 8514", "size": 10}, {"route": "35", "longitude": -122.435197, "d_time": 708, "time": 57240, "latitude": 37.762674, "trip": " 8514", "size": 10}, {"route": "35", "longitude": -122.43535, "d_time": 679, "time": 56760, "latitude": 37.741599, "trip": " 8514", "size": 10}, {"d_time": 679, "time": 57360, "latitude": 37.741599, "route": "35", "trip": " 8514", "longitude": -122.43535, "size": 0}], [{"d_time": 0, "time": 54780, "latitude": 37.737725, "route": "35", "trip": " 8517", "longitude": -122.429531, "size": 0}, {"route": "35", "longitude": -122.429531, "d_time": 0, "time": 54780, "latitude": 37.737725, "trip": " 8517", "size": 10}, {"route": "35", "longitude": -122.429531, "d_time": 0, "time": 55440, "latitude": 37.737725, "trip": " 8517", "size": 10}, {"route": "35", "longitude": -122.429531, "d_time": 0, "time": 54960, "latitude": 37.737725, "trip": " 8517", "size": 10}, {"route": "35", "longitude": -122.429531, "d_time": 366, "time": 52920, "latitude": 37.737725, "trip": " 8517", "size": 10}, {"route": "35", "longitude": -122.435197, "d_time": 827, "time": 53580, "latitude": 37.762674, "trip": " 8517", "size": 10}, {"route": "35", "longitude": -122.43535, "d_time": 493, "time": 53100, "latitude": 37.741599, "trip": " 8517", "size": 10}, {"route": "35", "longitude": -122.429531, "d_time": 161, "time": 51120, "latitude": 37.737725, "trip": " 8517", "size": 10}, {"route": "35", "longitude": -122.435197, "d_time": 281, "time": 51780, "latitude": 37.762674, "trip": " 8517", "size": 10}, {"route": "35", "longitude": -122.43535, "d_time": 145, "time": 51300, "latitude": 37.741599, "trip": " 8517", "size": 10}, {"route": "35", "longitude": -122.429531, "d_time": -21, "time": 49320, "latitude": 37.737725, "trip": " 8517", "size": 10}, {"route": "35", "longitude": -122.435197, "d_time": 97, "time": 49980, "latitude": 37.762674, "trip": " 8517", "size": 10}, {"route": "35", "longitude": -122.43535, "d_time": -10, "time": 49500, "latitude": 37.741599, "trip": " 8517", "size": 10}, {"route": "35", "longitude": -122.429531, "d_time": 103, "time": 47520, "latitude": 37.737725, "trip": " 8517", "size": 10}, {"route": "35", "longitude": -122.435197, "d_time": 108, "time": 48180, "latitude": 37.762674, "trip": " 8517", "size": 10}, {"route": "35", "longitude": -122.43535, "d_time": 95, "time": 47700, "latitude": 37.741599, "trip": " 8517", "size": 10}, {"d_time": 95, "time": 48300, "latitude": 37.741599, "route": "35", "trip": " 8517", "longitude": -122.43535, "size": 0}], [{"d_time": 173, "time": 88920, "latitude": 37.737725, "route": "35", "trip": " 8517", "longitude": -122.429531, "size": 0}, {"route": "35", "longitude": -122.429531, "d_time": 173, "time": 88920, "latitude": 37.737725, "trip": " 8517", "size": 10}, {"route": "35", "longitude": -122.435197, "d_time": 275, "time": 89580, "latitude": 37.762674, "trip": " 8517", "size": 10}, {"route": "35", "longitude": -122.43535, "d_time": 171, "time": 89100, "latitude": 37.741599, "trip": " 8517", "size": 10}, {"route": "35", "longitude": -122.429531, "d_time": 0, "time": 87120, "latitude": 37.737725, "trip": " 8517", "size": 10}, {"route": "35", "longitude": -122.429531, "d_time": 0, "time": 87780, "latitude": 37.737725, "trip": " 8517", "size": 10}, {"route": "35", "longitude": -122.429531, "d_time": 0, "time": 87300, "latitude": 37.737725, "trip": " 8517", "size": 10}, {"d_time": 0, "time": 87900, "latitude": 37.737725, "route": "35", "trip": " 8517", "longitude": -122.429531, "size": 0}], [{"d_time": 64, "time": 42120, "latitude": 37.737725, "route": "35", "trip": " 8517", "longitude": -122.429531, "size": 0}, {"route": "35", "longitude": -122.429531, "d_time": 64, "time": 42120, "latitude": 37.737725, "trip": " 8517", "size": 10}, {"route": "35", "longitude": -122.435197, "d_time": 112, "time": 42780, "latitude": 37.762674, "trip": " 8517", "size": 10}, {"route": "35", "longitude": -122.43535, "d_time": 30, "time": 42300, "latitude": 37.741599, "trip": " 8517", "size": 10}, {"route": "35", "longitude": -122.429531, "d_time": 191, "time": 40260, "latitude": 37.737725, "trip": " 8517", "size": 10}, {"route": "35", "longitude": -122.435197, "d_time": 204, "time": 40920, "latitude": 37.762674, "trip": " 8517", "size": 10}, {"route": "35", "longitude": -122.43535, "d_time": 156, "time": 40440, "latitude": 37.741599, "trip": " 8517", "size": 10}, {"route": "35", "longitude": -122.429531, "d_time": 214, "time": 38460, "latitude": 37.737725, "trip": " 8517", "size": 10}, {"route": "35", "longitude": -122.435197, "d_time": 261, "time": 39120, "latitude": 37.762674, "trip": " 8517", "size": 10}, {"route": "35", "longitude": -122.43535, "d_time": 174, "time": 38640, "latitude": 37.741599, "trip": " 8517", "size": 10}, {"route": "35", "longitude": -122.429531, "d_time": 193, "time": 36660, "latitude": 37.737725, "trip": " 8517", "size": 10}, {"route": "35", "longitude": -122.435197, "d_time": 218, "time": 37320, "latitude": 37.762674, "trip": " 8517", "size": 10}, {"route": "35", "longitude": -122.43535, "d_time": 186, "time": 36840, "latitude": 37.741599, "trip": " 8517", "size": 10}, {"route": "35", "longitude": -122.429531, "d_time": 121, "time": 34860, "latitude": 37.737725, "trip": " 8517", "size": 10}, {"route": "35", "longitude": -122.435197, "d_time": 161, "time": 35520, "latitude": 37.762674, "trip": " 8517", "size": 10}, {"route": "35", "longitude": -122.43535, "d_time": 128, "time": 35040, "latitude": 37.741599, "trip": " 8517", "size": 10}, {"route": "35", "longitude": -122.429531, "d_time": 102, "time": 33060, "latitude": 37.737725, "trip": " 8517", "size": 10}, {"route": "35", "longitude": -122.435197, "d_time": 81, "time": 33720, "latitude": 37.762674, "trip": " 8517", "size": 10}, {"route": "35", "longitude": -122.43535, "d_time": 62, "time": 33240, "latitude": 37.741599, "trip": " 8517", "size": 10}, {"route": "35", "longitude": -122.429531, "d_time": 75, "time": 31320, "latitude": 37.737725, "trip": " 8517", "size": 10}, {"route": "35", "longitude": -122.435197, "d_time": 157, "time": 31980, "latitude": 37.762674, "trip": " 8517", "size": 10}, {"route": "35", "longitude": -122.43535, "d_time": 79, "time": 31500, "latitude": 37.741599, "trip": " 8517", "size": 10}, {"route": "35", "longitude": -122.429531, "d_time": 77, "time": 29520, "latitude": 37.737725, "trip": " 8517", "size": 10}, {"route": "35", "longitude": -122.435197, "d_time": 121, "time": 30180, "latitude": 37.762674, "trip": " 8517", "size": 10}, {"route": "35", "longitude": -122.43535, "d_time": 68, "time": 29700, "latitude": 37.741599, "trip": " 8517", "size": 10}, {"d_time": 68, "time": 30300, "latitude": 37.741599, "route": "35", "trip": " 8517", "longitude": -122.43535, "size": 0}]]