[[{"d_time": 20, "time": 85500, "latitude": 37.76767, "route": "37", "trip": " 8517", "longitude": -122.42913, "size": 0}, {"route": "37", "longitude": -122.42913, "d_time": 20, "time": 85500, "latitude": 37.76767, "trip": " 8517", "size": 10}, {"route": "37", "longitude": -122.43538, "d_time": -16, "time": 85740, "latitude": 37.76262, "trip": " 8517", "size": 10}, {"route": "37", "longitude": -122.444766, "d_time": -45, "time": 86220, "latitude": 37.747042, "trip": " 8517", "size": 10}, {"route": "37", "longitude": -122.445407, "d_time": -15, "time": 84660, "latitude": 37.770089, "trip": " 8517", "size": 10}, {"d_time": -15, "time": 85260, "latitude": 37.770089, "route": "37", "trip": " 8517", "longitude": -122.445407, "size": 0}], [{"d_time": 0, "time": 43321, "latitude": 37.76767, "route": "37", "trip": " 8512", "longitude": -122.42913, "size": 0}, {"route": "37", "longitude": -122.42913, "d_time": 0, "time": 43321, "latitude": 37.76767, "trip": " 8512", "size": 10}, {"d_time": 0, "time": 43921, "latitude": 37.76767, "route": "37", "trip": " 8512", "longitude": -122.42913, "size": 0}], [{"d_time": -5, "time": 84420, "latitude": 37.76767, "route": "37", "trip": " 8512", "longitude": -122.42913, "size": 0}, {"route": "37", "longitude": -122.42913, "d_time": -5, "time": 84420, "latitude": 37.76767, "trip": " 8512", "size": 10}, {"route": "37", "longitude": -122.43538, "d_time": -29, "time": 84660, "latitude": 37.76262, "trip": " 8512", "size": 10}, {"route": "37", "longitude": -122.444766, "d_time": -54, "time": 85140, "latitude": 37.747042, "trip": " 8512", "size": 10}, {"route": "37", "longitude": -122.445407, "d_time": -17, "time": 83580, "latitude": 37.770089, "trip": " 8512", "size": 10}, {"d_time": -17, "time": 84180, "latitude": 37.770089, "route": "37", "trip": " 8512", "longitude": -122.445407, "size": 0}], [{"d_time": 0, "time": 85440, "latitude": 37.76767, "route": "37", "trip": " 8525", "longitude": -122.42913, "size": 0}, {"route": "37", "longitude": -122.42913, "d_time": 0, "time": 85440, "latitude": 37.76767, "trip": " 8525", "size": 10}, {"d_time": 0, "time": 86040, "latitude": 37.76767, "route": "37", "trip": " 8525", "longitude": -122.42913, "size": 0}], [{"d_time": 2, "time": 82620, "latitude": 37.76767, "route": "37", "trip": " 8525", "longitude": -122.42913, "size": 0}, {"route": "37", "longitude": -122.42913, "d_time": 2, "time": 82620, "latitude": 37.76767, "trip": " 8525", "size": 10}, {"route": "37", "longitude": -122.43538, "d_time": -50, "time": 82860, "latitude": 37.76262, "trip": " 8525", "size": 10}, {"route": "37", "longitude": -122.444766, "d_time": 48, "time": 83340, "latitude": 37.747042, "trip": " 8525", "size": 10}, {"route": "37", "longitude": -122.445407, "d_time": 27, "time": 81780, "latitude": 37.770089, "trip": " 8525", "size": 10}, {"route": "37", "longitude": -122.44578, "d_time": 57, "time": 83640, "latitude": 37.75041, "trip": " 8525", "size": 10}, {"d_time": 57, "time": 84240, "latitude": 37.75041, "route": "37", "trip": " 8525", "longitude": -122.44578, "size": 0}], [{"d_time": 31, "time": 80820, "latitude": 37.76767, "route": "37", "trip": " 8517", "longitude": -122.42913, "size": 0}, {"route": "37", "longitude": -122.42913, "d_time": 31, "time": 80820, "latitude": 37.76767, "trip": " 8517", "size": 10}, {"route": "37", "longitude": -122.43538, "d_time": -53, "time": 81060, "latitude": 37.76262, "trip": " 8517", "size": 10}, {"route": "37", "longitude": -122.444766, "d_time": 34, "time": 81540, "latitude": 37.747042, "trip": " 8517", "size": 10}, {"route": "37", "longitude": -122.445407, "d_time": 61, "time": 79980, "latitude": 37.770089, "trip": " 8517", "size": 10}, {"route": "37", "longitude": -122.44578, "d_time": 150, "time": 81840, "latitude": 37.75041, "trip": " 8517", "size": 10}, {"d_time": 150, "time": 82440, "latitude": 37.75041, "route": "37", "trip": " 8517", "longitude": -122.44578, "size": 0}], [{"d_time": 98, "time": 79020, "latitude": 37.76767, "route": "37", "trip": " 8512", "longitude": -122.42913, "size": 0}, {"route": "37", "longitude": -122.42913, "d_time": 98, "time": 79020, "latitude": 37.76767, "trip": " 8512", "size": 10}, {"route": "37", "longitude": -122.43538, "d_time": 64, "time": 79260, "latitude": 37.76262, "trip": " 8512", "size": 10}, {"route": "37", "longitude": -122.444766, "d_time": 17, "time": 79740, "latitude": 37.747042, "trip": " 8512", "size": 10}, {"route": "37", "longitude": -122.445407, "d_time": 1, "time": 78180, "latitude": 37.770089, "trip": " 8512", "size": 10}, {"route": "37", "longitude": -122.44578, "d_time": -6, "time": 80040, "latitude": 37.75041, "trip": " 8512", "size": 10}, {"d_time": -6, "time": 80640, "latitude": 37.75041, "route": "37", "trip": " 8512", "longitude": -122.44578, "size": 0}], [{"d_time": 101, "time": 77220, "latitude": 37.76767, "route": "37", "trip": " 8525", "longitude": -122.42913, "size": 0}, {"route": "37", "longitude": -122.42913, "d_time": 101, "time": 77220, "latitude": 37.76767, "trip": " 8525", "size": 10}, {"route": "37", "longitude": -122.43538, "d_time": 47, "time": 77460, "latitude": 37.76262, "trip": " 8525", "size": 10}, {"route": "37", "longitude": -122.444766, "d_time": 142, "time": 77940, "latitude": 37.747042, "trip": " 8525", "size": 10}, {"route": "37", "longitude": -122.445407, "d_time": -3, "time": 76380, "latitude": 37.770089, "trip": " 8525", "size": 10}, {"route": "37", "longitude": -122.44578, "d_time": 167, "time": 78240, "latitude": 37.75041, "trip": " 8525", "size": 10}, {"d_time": 167, "time": 78840, "latitude": 37.75041, "route": "37", "trip": " 8525", "longitude": -122.44578, "size": 0}], [{"d_time": 119, "time": 75420, "latitude": 37.76767, "route": "37", "trip": " 8517", "longitude": -122.42913, "size": 0}, {"route": "37", "longitude": -122.42913, "d_time": 119, "time": 75420, "latitude": 37.76767, "trip": " 8517", "size": 10}, {"route": "37", "longitude": -122.43538, "d_time": 41, "time": 75660, "latitude": 37.76262, "trip": " 8517", "size": 10}, {"route": "37", "longitude": -122.444766, "d_time": 57, "time": 76140, "latitude": 37.747042, "trip": " 8517", "size": 10}, {"route": "37", "longitude": -122.445407, "d_time": -12, "time": 74580, "latitude": 37.770089, "trip": " 8517", "size": 10}, {"route": "37", "longitude": -122.44578, "d_time": 88, "time": 76440, "latitude": 37.75041, "trip": " 8517", "size": 10}, {"d_time": 88, "time": 77040, "latitude": 37.75041, "route": "37", "trip": " 8517", "longitude": -122.44578, "size": 0}], [{"d_time": 55, "time": 73620, "latitude": 37.76767, "route": "37", "trip": " 8512", "longitude": -122.42913, "size": 0}, {"route": "37", "longitude": -122.42913, "d_time": 55, "time": 73620, "latitude": 37.76767, "trip": " 8512", "size": 10}, {"route": "37", "longitude": -122.43538, "d_time": -46, "time": 73860, "latitude": 37.76262, "trip": " 8512", "size": 10}, {"route": "37", "longitude": -122.444766, "d_time": -35, "time": 74340, "latitude": 37.747042, "trip": " 8512", "size": 10}, {"route": "37", "longitude": -122.445407, "d_time": -5, "time": 72780, "latitude": 37.770089, "trip": " 8512", "size": 10}, {"route": "37", "longitude": -122.44578, "d_time": 142, "time": 74640, "latitude": 37.75041, "trip": " 8512", "size": 10}, {"d_time": 142, "time": 75240, "latitude": 37.75041, "route": "37", "trip": " 8512", "longitude": -122.44578, "size": 0}], [{"d_time": 297, "time": 71820, "latitude": 37.76767, "route": "37", "trip": " 8525", "longitude": -122.42913, "size": 0}, {"route": "37", "longitude": -122.42913, "d_time": 297, "time": 71820, "latitude": 37.76767, "trip": " 8525", "size": 10}, {"route": "37", "longitude": -122.43538, "d_time": 279, "time": 72060, "latitude": 37.76262, "trip": " 8525", "size": 10}, {"route": "37", "longitude": -122.444766, "d_time": 477, "time": 72540, "latitude": 37.747042, "trip": " 8525", "size": 10}, {"route": "37", "longitude": -122.445407, "d_time": -20, "time": 70980, "latitude": 37.770089, "trip": " 8525", "size": 10}, {"route": "37", "longitude": -122.44578, "d_time": 521, "time": 72840, "latitude": 37.75041, "trip": " 8525", "size": 10}, {"d_time": 521, "time": 73440, "latitude": 37.75041, "route": "37", "trip": " 8525", "longitude": -122.44578, "size": 0}], [{"d_time": 142, "time": 70020, "latitude": 37.76767, "route": "37", "trip": " 8514", "longitude": -122.42913, "size": 0}, {"route": "37", "longitude": -122.42913, "d_time": 142, "time": 70020, "latitude": 37.76767, "trip": " 8514", "size": 10}, {"route": "37", "longitude": -122.43538, "d_time": 124, "time": 70260, "latitude": 37.76262, "trip": " 8514", "size": 10}, {"route": "37", "longitude": -122.444766, "d_time": 210, "time": 70740, "latitude": 37.747042, "trip": " 8514", "size": 10}, {"route": "37", "longitude": -122.445407, "d_time": 11, "time": 69180, "latitude": 37.770089, "trip": " 8514", "size": 10}, {"route": "37", "longitude": -122.44578, "d_time": 233, "time": 71040, "latitude": 37.75041, "trip": " 8514", "size": 10}, {"d_time": 233, "time": 71640, "latitude": 37.75041, "route": "37", "trip": " 8514", "longitude": -122.44578, "size": 0}], [{"d_time": 205, "time": 68820, "latitude": 37.76767, "route": "37", "trip": " 8517", "longitude": -122.42913, "size": 0}, {"route": "37", "longitude": -122.42913, "d_time": 205, "time": 68820, "latitude": 37.76767, "trip": " 8517", "size": 10}, {"route": "37", "longitude": -122.43538, "d_time": 153, "time": 69060, "latitude": 37.76262, "trip": " 8517", "size": 10}, {"route": "37", "longitude": -122.444766, "d_time": 273, "time": 69540, "latitude": 37.747042, "trip": " 8517", "size": 10}, {"route": "37", "longitude": -122.445407, "d_time": 54, "time": 67980, "latitude": 37.770089, "trip": " 8517", "size": 10}, {"route": "37", "longitude": -122.44578, "d_time": 445, "time": 69840, "latitude": 37.75041, "trip": " 8517", "size": 10}, {"d_time": 445, "time": 70440, "latitude": 37.75041, "route": "37", "trip": " 8517", "longitude": -122.44578, "size": 0}], [{"d_time": 89, "time": 66420, "latitude": 37.76767, "route": "37", "trip": " 8525", "longitude": -122.42913, "size": 0}, {"route": "37", "longitude": -122.42913, "d_time": 89, "time": 66420, "latitude": 37.76767, "trip": " 8525", "size": 10}, {"route": "37", "longitude": -122.43538, "d_time": 45, "time": 66660, "latitude": 37.76262, "trip": " 8525", "size": 10}, {"route": "37", "longitude": -122.444766, "d_time": 225, "time": 67140, "latitude": 37.747042, "trip": " 8525", "size": 10}, {"route": "37", "longitude": -122.445407, "d_time": -19, "time": 65580, "latitude": 37.770089, "trip": " 8525", "size": 10}, {"route": "37", "longitude": -122.44578, "d_time": 626, "time": 67440, "latitude": 37.75041, "trip": " 8525", "size": 10}, {"d_time": 626, "time": 68040, "latitude": 37.75041, "route": "37", "trip": " 8525", "longitude": -122.44578, "size": 0}], [{"d_time": -70, "time": 65220, "latitude": 37.76767, "route": "37", "trip": " 8514", "longitude": -122.42913, "size": 0}, {"route": "37", "longitude": -122.42913, "d_time": -70, "time": 65220, "latitude": 37.76767, "trip": " 8514", "size": 10}, {"route": "37", "longitude": -122.43538, "d_time": -101, "time": 65460, "latitude": 37.76262, "trip": " 8514", "size": 10}, {"route": "37", "longitude": -122.444766, "d_time": 49, "time": 65940, "latitude": 37.747042, "trip": " 8514", "size": 10}, {"route": "37", "longitude": -122.445407, "d_time": 15, "time": 64380, "latitude": 37.770089, "trip": " 8514", "size": 10}, {"route": "37", "longitude": -122.44578, "d_time": 134, "time": 66240, "latitude": 37.75041, "trip": " 8514", "size": 10}, {"d_time": 134, "time": 66840, "latitude": 37.75041, "route": "37", "trip": " 8514", "longitude": -122.44578, "size": 0}], [{"d_time": 250, "time": 64020, "latitude": 37.76767, "route": "37", "trip": " 8517", "longitude": -122.42913, "size": 0}, {"route": "37", "longitude": -122.42913, "d_time": 250, "time": 64020, "latitude": 37.76767, "trip": " 8517", "size": 10}, {"route": "37", "longitude": -122.43538, "d_time": 291, "time": 64260, "latitude": 37.76262, "trip": " 8517", "size": 10}, {"route": "37", "longitude": -122.444766, "d_time": 492, "time": 64740, "latitude": 37.747042, "trip": " 8517", "size": 10}, {"route": "37", "longitude": -122.445407, "d_time": 99, "time": 63180, "latitude": 37.770089, "trip": " 8517", "size": 10}, {"route": "37", "longitude": -122.44578, "d_time": 638, "time": 65040, "latitude": 37.75041, "trip": " 8517", "size": 10}, {"d_time": 638, "time": 65640, "latitude": 37.75041, "route": "37", "trip": " 8517", "longitude": -122.44578, "size": 0}], [{"d_time": 103, "time": 62820, "latitude": 37.76767, "route": "37", "trip": " 8512", "longitude": -122.42913, "size": 0}, {"route": "37", "longitude": -122.42913, "d_time": 103, "time": 62820, "latitude": 37.76767, "trip": " 8512", "size": 10}, {"route": "37", "longitude": -122.43538, "d_time": 6, "time": 63060, "latitude": 37.76262, "trip": " 8512", "size": 10}, {"route": "37", "longitude": -122.444766, "d_time": 111, "time": 63540, "latitude": 37.747042, "trip": " 8512", "size": 10}, {"route": "37", "longitude": -122.445407, "d_time": -47, "time": 61980, "latitude": 37.770089, "trip": " 8512", "size": 10}, {"route": "37", "longitude": -122.44578, "d_time": 162, "time": 63840, "latitude": 37.75041, "trip": " 8512", "size": 10}, {"d_time": 162, "time": 64440, "latitude": 37.75041, "route": "37", "trip": " 8512", "longitude": -122.44578, "size": 0}], [{"d_time": 103, "time": 61620, "latitude": 37.76767, "route": "37", "trip": " 8525", "longitude": -122.42913, "size": 0}, {"route": "37", "longitude": -122.42913, "d_time": 103, "time": 61620, "latitude": 37.76767, "trip": " 8525", "size": 10}, {"route": "37", "longitude": -122.43538, "d_time": 82, "time": 61860, "latitude": 37.76262, "trip": " 8525", "size": 10}, {"route": "37", "longitude": -122.444766, "d_time": 264, "time": 62340, "latitude": 37.747042, "trip": " 8525", "size": 10}, {"route": "37", "longitude": -122.445407, "d_time": 24, "time": 60780, "latitude": 37.770089, "trip": " 8525", "size": 10}, {"route": "37", "longitude": -122.44578, "d_time": 323, "time": 62640, "latitude": 37.75041, "trip": " 8525", "size": 10}, {"d_time": 323, "time": 63240, "latitude": 37.75041, "route": "37", "trip": " 8525", "longitude": -122.44578, "size": 0}], [{"d_time": 49, "time": 60420, "latitude": 37.76767, "route": "37", "trip": " 8514", "longitude": -122.42913, "size": 0}, {"route": "37", "longitude": -122.42913, "d_time": 49, "time": 60420, "latitude": 37.76767, "trip": " 8514", "size": 10}, {"route": "37", "longitude": -122.43538, "d_time": -11, "time": 60660, "latitude": 37.76262, "trip": " 8514", "size": 10}, {"route": "37", "longitude": -122.444766, "d_time": 175, "time": 61140, "latitude": 37.747042, "trip": " 8514", "size": 10}, {"route": "37", "longitude": -122.445407, "d_time": -30, "time": 59580, "latitude": 37.770089, "trip": " 8514", "size": 10}, {"route": "37", "longitude": -122.44578, "d_time": 178, "time": 61440, "latitude": 37.75041, "trip": " 8514", "size": 10}, {"d_time": 178, "time": 62040, "latitude": 37.75041, "route": "37", "trip": " 8514", "longitude": -122.44578, "size": 0}], [{"d_time": 205, "time": 59220, "latitude": 37.76767, "route": "37", "trip": " 8517", "longitude": -122.42913, "size": 0}, {"route": "37", "longitude": -122.42913, "d_time": 205, "time": 59220, "latitude": 37.76767, "trip": " 8517", "size": 10}, {"route": "37", "longitude": -122.43538, "d_time": 118, "time": 59460, "latitude": 37.76262, "trip": " 8517", "size": 10}, {"route": "37", "longitude": -122.444766, "d_time": 245, "time": 59940, "latitude": 37.747042, "trip": " 8517", "size": 10}, {"route": "37", "longitude": -122.445407, "d_time": -35, "time": 58380, "latitude": 37.770089, "trip": " 8517", "size": 10}, {"route": "37", "longitude": -122.44578, "d_time": 258, "time": 60240, "latitude": 37.75041, "trip": " 8517", "size": 10}, {"d_time": 258, "time": 60840, "latitude": 37.75041, "route": "37", "trip": " 8517", "longitude": -122.44578, "size": 0}], [{"d_time": 44, "time": 58020, "latitude": 37.76767, "route": "37", "trip": " 8512", "longitude": -122.42913, "size": 0}, {"route": "37", "longitude": -122.42913, "d_time": 44, "time": 58020, "latitude": 37.76767, "trip": " 8512", "size": 10}, {"route": "37", "longitude": -122.43538, "d_time": -16, "time": 58260, "latitude": 37.76262, "trip": " 8512", "size": 10}, {"route": "37", "longitude": -122.444766, "d_time": 142, "time": 58740, "latitude": 37.747042, "trip": " 8512", "size": 10}, {"route": "37", "longitude": -122.445407, "d_time": 74, "time": 57180, "latitude": 37.770089, "trip": " 8512", "size": 10}, {"route": "37", "longitude": -122.44578, "d_time": 193, "time": 59040, "latitude": 37.75041, "trip": " 8512", "size": 10}, {"d_time": 193, "time": 59640, "latitude": 37.75041, "route": "37", "trip": " 8512", "longitude": -122.44578, "size": 0}], [{"d_time": 58, "time": 56820, "latitude": 37.76767, "route": "37", "trip": " 8525", "longitude": -122.42913, "size": 0}, {"route": "37", "longitude": -122.42913, "d_time": 58, "time": 56820, "latitude": 37.76767, "trip": " 8525", "size": 10}, {"route": "37", "longitude": -122.43538, "d_time": 6, "time": 57060, "latitude": 37.76262, "trip": " 8525", "size": 10}, {"route": "37", "longitude": -122.444766, "d_time": 165, "time": 57540, "latitude": 37.747042, "trip": " 8525", "size": 10}, {"route": "37", "longitude": -122.445407, "d_time": 34, "time": 55980, "latitude": 37.770089, "trip": " 8525", "size": 10}, {"route": "37", "longitude": -122.44578, "d_time": 262, "time": 57840, "latitude": 37.75041, "trip": " 8525", "size": 10}, {"d_time": 262, "time": 58440, "latitude": 37.75041, "route": "37", "trip": " 8525", "longitude": -122.44578, "size": 0}], [{"d_time": 98, "time": 55620, "latitude": 37.76767, "route": "37", "trip": " 8514", "longitude": -122.42913, "size": 0}, {"route": "37", "longitude": -122.42913, "d_time": 98, "time": 55620, "latitude": 37.76767, "trip": " 8514", "size": 10}, {"route": "37", "longitude": -122.43538, "d_time": 38, "time": 55860, "latitude": 37.76262, "trip": " 8514", "size": 10}, {"route": "37", "longitude": -122.444766, "d_time": 58, "time": 56340, "latitude": 37.747042, "trip": " 8514", "size": 10}, {"route": "37", "longitude": -122.445407, "d_time": -7, "time": 54780, "latitude": 37.770089, "trip": " 8514", "size": 10}, {"route": "37", "longitude": -122.44578, "d_time": 157, "time": 56640, "latitude": 37.75041, "trip": " 8514", "size": 10}, {"d_time": 157, "time": 57240, "latitude": 37.75041, "route": "37", "trip": " 8514", "longitude": -122.44578, "size": 0}], [{"d_time": 56, "time": 54420, "latitude": 37.76767, "route": "37", "trip": " 8517", "longitude": -122.42913, "size": 0}, {"route": "37", "longitude": -122.42913, "d_time": 56, "time": 54420, "latitude": 37.76767, "trip": " 8517", "size": 10}, {"route": "37", "longitude": -122.43538, "d_time": -80, "time": 54660, "latitude": 37.76262, "trip": " 8517", "size": 10}, {"route": "37", "longitude": -122.444766, "d_time": 68, "time": 55140, "latitude": 37.747042, "trip": " 8517", "size": 10}, {"route": "37", "longitude": -122.445407, "d_time": -4, "time": 53580, "latitude": 37.770089, "trip": " 8517", "size": 10}, {"route": "37", "longitude": -122.44578, "d_time": 49, "time": 55440, "latitude": 37.75041, "trip": " 8517", "size": 10}, {"d_time": 49, "time": 56040, "latitude": 37.75041, "route": "37", "trip": " 8517", "longitude": -122.44578, "size": 0}], [{"d_time": 68, "time": 53220, "latitude": 37.76767, "route": "37", "trip": " 8512", "longitude": -122.42913, "size": 0}, {"route": "37", "longitude": -122.42913, "d_time": 68, "time": 53220, "latitude": 37.76767, "trip": " 8512", "size": 10}, {"route": "37", "longitude": -122.43538, "d_time": -42, "time": 53460, "latitude": 37.76262, "trip": " 8512", "size": 10}, {"route": "37", "longitude": -122.444766, "d_time": -111, "time": 53940, "latitude": 37.747042, "trip": " 8512", "size": 10}, {"route": "37", "longitude": -122.445407, "d_time": 21, "time": 52380, "latitude": 37.770089, "trip": " 8512", "size": 10}, {"route": "37", "longitude": -122.44578, "d_time": 43, "time": 54240, "latitude": 37.75041, "trip": " 8512", "size": 10}, {"d_time": 43, "time": 54840, "latitude": 37.75041, "route": "37", "trip": " 8512", "longitude": -122.44578, "size": 0}], [{"d_time": 934, "time": 52020, "latitude": 37.76767, "route": "37", "trip": " 8525", "longitude": -122.42913, "size": 0}, {"route": "37", "longitude": -122.42913, "d_time": 934, "time": 52020, "latitude": 37.76767, "trip": " 8525", "size": 10}, {"route": "37", "longitude": -122.43538, "d_time": 946, "time": 52260, "latitude": 37.76262, "trip": " 8525", "size": 10}, {"route": "37", "longitude": -122.444766, "d_time": 1042, "time": 52740, "latitude": 37.747042, "trip": " 8525", "size": 10}, {"route": "37", "longitude": -122.445407, "d_time": 515, "time": 51180, "latitude": 37.770089, "trip": " 8525", "size": 10}, {"route": "37", "longitude": -122.44578, "d_time": 1067, "time": 53040, "latitude": 37.75041, "trip": " 8525", "size": 10}, {"d_time": 1067, "time": 53640, "latitude": 37.75041, "route": "37", "trip": " 8525", "longitude": -122.44578, "size": 0}], [{"d_time": 162, "time": 50820, "latitude": 37.76767, "route": "37", "trip": " 8514", "longitude": -122.42913, "size": 0}, {"route": "37", "longitude": -122.42913, "d_time": 162, "time": 50820, "latitude": 37.76767, "trip": " 8514", "size": 10}, {"route": "37", "longitude": -122.43538, "d_time": 81, "time": 51060, "latitude": 37.76262, "trip": " 8514", "size": 10}, {"route": "37", "longitude": -122.444766, "d_time": 108, "time": 51540, "latitude": 37.747042, "trip": " 8514", "size": 10}, {"route": "37", "longitude": -122.445407, "d_time": 11, "time": 49980, "latitude": 37.770089, "trip": " 8514", "size": 10}, {"route": "37", "longitude": -122.44578, "d_time": 187, "time": 51840, "latitude": 37.75041, "trip": " 8514", "size": 10}, {"d_time": 187, "time": 52440, "latitude": 37.75041, "route": "37", "trip": " 8514", "longitude": -122.44578, "size": 0}], [{"d_time": 96, "time": 49620, "latitude": 37.76767, "route": "37", "trip": " 8517", "longitude": -122.42913, "size": 0}, {"route": "37", "longitude": -122.42913, "d_time": 96, "time": 49620, "latitude": 37.76767, "trip": " 8517", "size": 10}, {"route": "37", "longitude": -122.43538, "d_time": 17, "time": 49860, "latitude": 37.76262, "trip": " 8517", "size": 10}, {"route": "37", "longitude": -122.444766, "d_time": 211, "time": 50340, "latitude": 37.747042, "trip": " 8517", "size": 10}, {"route": "37", "longitude": -122.445407, "d_time": -34, "time": 48780, "latitude": 37.770089, "trip": " 8517", "size": 10}, {"route": "37", "longitude": -122.44578, "d_time": 582, "time": 50640, "latitude": 37.75041, "trip": " 8517", "size": 10}, {"d_time": 582, "time": 51240, "latitude": 37.75041, "route": "37", "trip": " 8517", "longitude": -122.44578, "size": 0}], [{"d_time": 112, "time": 48420, "latitude": 37.76767, "route": "37", "trip": " 8512", "longitude": -122.42913, "size": 0}, {"route": "37", "longitude": -122.42913, "d_time": 112, "time": 48420, "latitude": 37.76767, "trip": " 8512", "size": 10}, {"route": "37", "longitude": -122.43538, "d_time": 50, "time": 48660, "latitude": 37.76262, "trip": " 8512", "size": 10}, {"route": "37", "longitude": -122.444766, "d_time": 40, "time": 49140, "latitude": 37.747042, "trip": " 8512", "size": 10}, {"route": "37", "longitude": -122.445407, "d_time": -38, "time": 47580, "latitude": 37.770089, "trip": " 8512", "size": 10}, {"route": "37", "longitude": -122.44578, "d_time": 67, "time": 49440, "latitude": 37.75041, "trip": " 8512", "size": 10}, {"d_time": 67, "time": 50040, "latitude": 37.75041, "route": "37", "trip": " 8512", "longitude": -122.44578, "size": 0}], [{"d_time": 402, "time": 47220, "latitude": 37.76767, "route": "37", "trip": " 8525", "longitude": -122.42913, "size": 0}, {"route": "37", "longitude": -122.42913, "d_time": 402, "time": 47220, "latitude": 37.76767, "trip": " 8525", "size": 10}, {"route": "37", "longitude": -122.43538, "d_time": 525, "time": 47460, "latitude": 37.76262, "trip": " 8525", "size": 10}, {"route": "37", "longitude": -122.444766, "d_time": 769, "time": 47940, "latitude": 37.747042, "trip": " 8525", "size": 10}, {"d_time": 769, "time": 48540, "latitude": 37.747042, "route": "37", "trip": " 8525", "longitude": -122.444766, "size": 0}], [{"d_time": 144, "time": 89580, "latitude": 37.770089, "route": "37", "trip": " 8525", "longitude": -122.445407, "size": 0}, {"route": "37", "longitude": -122.445407, "d_time": 144, "time": 89580, "latitude": 37.770089, "trip": " 8525", "size": 10}, {"d_time": 144, "time": 90180, "latitude": 37.770089, "route": "37", "trip": " 8525", "longitude": -122.445407, "size": 0}], [{"d_time": 887, "time": 48240, "latitude": 37.75041, "route": "37", "trip": " 8525", "longitude": -122.44578, "size": 0}, {"route": "37", "longitude": -122.44578, "d_time": 887, "time": 48240, "latitude": 37.75041, "trip": " 8525", "size": 10}, {"d_time": 887, "time": 48840, "latitude": 37.75041, "route": "37", "trip": " 8525", "longitude": -122.44578, "size": 0}], [{"d_time": 84, "time": 89220, "latitude": 37.76767, "route": "37", "trip": " 8514", "longitude": -122.42913, "size": 0}, {"route": "37", "longitude": -122.42913, "d_time": 84, "time": 89220, "latitude": 37.76767, "trip": " 8514", "size": 10}, {"route": "37", "longitude": -122.43538, "d_time": 107, "time": 89460, "latitude": 37.76262, "trip": " 8514", "size": 10}, {"route": "37", "longitude": -122.444766, "d_time": -43116, "time": 89940, "latitude": 37.747042, "trip": " 8514", "size": 10}, {"route": "37", "longitude": -122.445407, "d_time": -51, "time": 88380, "latitude": 37.770089, "trip": " 8514", "size": 10}, {"d_time": -51, "time": 88980, "latitude": 37.770089, "route": "37", "trip": " 8514", "longitude": -122.445407, "size": 0}], [{"d_time": -6, "time": 47040, "latitude": 37.75041, "route": "37", "trip": " 8514", "longitude": -122.44578, "size": 0}, {"route": "37", "longitude": -122.44578, "d_time": -6, "time": 47040, "latitude": 37.75041, "trip": " 8514", "size": 10}, {"d_time": -6, "time": 47640, "latitude": 37.75041, "route": "37", "trip": " 8514", "longitude": -122.44578, "size": 0}], [{"d_time": 124, "time": 88020, "latitude": 37.76767, "route": "37", "trip": " 8517", "longitude": -122.42913, "size": 0}, {"route": "37", "longitude": -122.42913, "d_time": 124, "time": 88020, "latitude": 37.76767, "trip": " 8517", "size": 10}, {"route": "37", "longitude": -122.43538, "d_time": 128, "time": 88260, "latitude": 37.76262, "trip": " 8517", "size": 10}, {"route": "37", "longitude": -122.444766, "d_time": 215, "time": 88740, "latitude": 37.747042, "trip": " 8517", "size": 10}, {"route": "37", "longitude": -122.445407, "d_time": 64, "time": 87180, "latitude": 37.770089, "trip": " 8517", "size": 10}, {"route": "37", "longitude": -122.44578, "d_time": 230, "time": 89040, "latitude": 37.75041, "trip": " 8517", "size": 10}, {"d_time": 230, "time": 89640, "latitude": 37.75041, "route": "37", "trip": " 8517", "longitude": -122.44578, "size": 0}], [{"d_time": 142, "time": 86820, "latitude": 37.76767, "route": "37", "trip": " 8512", "longitude": -122.42913, "size": 0}, {"route": "37", "longitude": -122.42913, "d_time": 142, "time": 86820, "latitude": 37.76767, "trip": " 8512", "size": 10}, {"route": "37", "longitude": -122.43538, "d_time": 82, "time": 87060, "latitude": 37.76262, "trip": " 8512", "size": 10}, {"route": "37", "longitude": -122.444766, "d_time": 101, "time": 87540, "latitude": 37.747042, "trip": " 8512", "size": 10}, {"d_time": 101, "time": 88140, "latitude": 37.747042, "route": "37", "trip": " 8512", "longitude": -122.444766, "size": 0}], [{"d_time": -8, "time": 42780, "latitude": 37.770089, "route": "37", "trip": " 8512", "longitude": -122.445407, "size": 0}, {"route": "37", "longitude": -122.445407, "d_time": -8, "time": 42780, "latitude": 37.770089, "trip": " 8512", "size": 10}, {"d_time": -8, "time": 43380, "latitude": 37.770089, "route": "37", "trip": " 8512", "longitude": -122.445407, "size": 0}], [{"d_time": 111, "time": 87840, "latitude": 37.75041, "route": "37", "trip": " 8512", "longitude": -122.44578, "size": 0}, {"route": "37", "longitude": -122.44578, "d_time": 111, "time": 87840, "latitude": 37.75041, "trip": " 8512", "size": 10}, {"d_time": 111, "time": 88440, "latitude": 37.75041, "route": "37", "trip": " 8512", "longitude": -122.44578, "size": 0}], [{"d_time": 555, "time": 42420, "latitude": 37.76767, "route": "37", "trip": " 8525", "longitude": -122.42913, "size": 0}, {"route": "37", "longitude": -122.42913, "d_time": 555, "time": 42420, "latitude": 37.76767, "trip": " 8525", "size": 10}, {"route": "37", "longitude": -122.43538, "d_time": 473, "time": 42660, "latitude": 37.76262, "trip": " 8525", "size": 10}, {"route": "37", "longitude": -122.444766, "d_time": 43836, "time": 43140, "latitude": 37.747042, "trip": " 8525", "size": 10}, {"route": "37", "longitude": -122.445407, "d_time": 249, "time": 41580, "latitude": 37.770089, "trip": " 8525", "size": 10}, {"d_time": 249, "time": 42180, "latitude": 37.770089, "route": "37", "trip": " 8525", "longitude": -122.445407, "size": 0}], [{"d_time": 722, "time": 86640, "latitude": 37.75041, "route": "37", "trip": " 8525", "longitude": -122.44578, "size": 0}, {"route": "37", "longitude": -122.44578, "d_time": 722, "time": 86640, "latitude": 37.75041, "trip": " 8525", "size": 10}, {"d_time": 722, "time": 87240, "latitude": 37.75041, "route": "37", "trip": " 8525", "longitude": -122.44578, "size": 0}], [{"d_time": 288, "time": 41220, "latitude": 37.76767, "route": "37", "trip": " 8514", "longitude": -122.42913, "size": 0}, {"route": "37", "longitude": -122.42913, "d_time": 288, "time": 41220, "latitude": 37.76767, "trip": " 8514", "size": 10}, {"route": "37", "longitude": -122.43538, "d_time": 224, "time": 41460, "latitude": 37.76262, "trip": " 8514", "size": 10}, {"route": "37", "longitude": -122.444766, "d_time": 219, "time": 41940, "latitude": 37.747042, "trip": " 8514", "size": 10}, {"route": "37", "longitude": -122.445407, "d_time": 48, "time": 40380, "latitude": 37.770089, "trip": " 8514", "size": 10}, {"route": "37", "longitude": -122.44578, "d_time": 167, "time": 42240, "latitude": 37.75041, "trip": " 8514", "size": 10}, {"d_time": 167, "time": 42840, "latitude": 37.75041, "route": "37", "trip": " 8514", "longitude": -122.44578, "size": 0}], [{"d_time": 149, "time": 40020, "latitude": 37.76767, "route": "37", "trip": " 8517", "longitude": -122.42913, "size": 0}, {"route": "37", "longitude": -122.42913, "d_time": 149, "time": 40020, "latitude": 37.76767, "trip": " 8517", "size": 10}, {"route": "37", "longitude": -122.43538, "d_time": 84, "time": 40260, "latitude": 37.76262, "trip": " 8517", "size": 10}, {"route": "37", "longitude": -122.444766, "d_time": 62, "time": 40740, "latitude": 37.747042, "trip": " 8517", "size": 10}, {"route": "37", "longitude": -122.445407, "d_time": 6, "time": 39180, "latitude": 37.770089, "trip": " 8517", "size": 10}, {"route": "37", "longitude": -122.44578, "d_time": 122, "time": 41040, "latitude": 37.75041, "trip": " 8517", "size": 10}, {"d_time": 122, "time": 41640, "latitude": 37.75041, "route": "37", "trip": " 8517", "longitude": -122.44578, "size": 0}], [{"d_time": 82, "time": 38820, "latitude": 37.76767, "route": "37", "trip": " 8512", "longitude": -122.42913, "size": 0}, {"route": "37", "longitude": -122.42913, "d_time": 82, "time": 38820, "latitude": 37.76767, "trip": " 8512", "size": 10}, {"route": "37", "longitude": -122.43538, "d_time": 17, "time": 39060, "latitude": 37.76262, "trip": " 8512", "size": 10}, {"route": "37", "longitude": -122.444766, "d_time": 7, "time": 39540, "latitude": 37.747042, "trip": " 8512", "size": 10}, {"route": "37", "longitude": -122.445407, "d_time": 112, "time": 37980, "latitude": 37.770089, "trip": " 8512", "size": 10}, {"route": "37", "longitude": -122.44578, "d_time": 4, "time": 39840, "latitude": 37.75041, "trip": " 8512", "size": 10}, {"d_time": 4, "time": 40440, "latitude": 37.75041, "route": "37", "trip": " 8512", "longitude": -122.44578, "size": 0}], [{"d_time": 234, "time": 37620, "latitude": 37.76767, "route": "37", "trip": " 8525", "longitude": -122.42913, "size": 0}, {"route": "37", "longitude": -122.42913, "d_time": 234, "time": 37620, "latitude": 37.76767, "trip": " 8525", "size": 10}, {"route": "37", "longitude": -122.43538, "d_time": 150, "time": 37860, "latitude": 37.76262, "trip": " 8525", "size": 10}, {"route": "37", "longitude": -122.444766, "d_time": 144, "time": 38340, "latitude": 37.747042, "trip": " 8525", "size": 10}, {"route": "37", "longitude": -122.44578, "d_time": 144, "time": 36780, "latitude": 37.75041, "trip": " 8525", "size": 10}, {"route": "37", "longitude": -122.44578, "d_time": 203, "time": 38640, "latitude": 37.75041, "trip": " 8525", "size": 10}, {"d_time": 203, "time": 39240, "latitude": 37.75041, "route": "37", "trip": " 8525", "longitude": -122.44578, "size": 0}], [{"d_time": -29, "time": 36420, "latitude": 37.76767, "route": "37", "trip": " 8514", "longitude": -122.42913, "size": 0}, {"route": "37", "longitude": -122.42913, "d_time": -29, "time": 36420, "latitude": 37.76767, "trip": " 8514", "size": 10}, {"route": "37", "longitude": -122.43538, "d_time": -9, "time": 36660, "latitude": 37.76262, "trip": " 8514", "size": 10}, {"route": "37", "longitude": -122.444766, "d_time": -91, "time": 37140, "latitude": 37.747042, "trip": " 8514", "size": 10}, {"route": "37", "longitude": -122.445407, "d_time": -17, "time": 35580, "latitude": 37.770089, "trip": " 8514", "size": 10}, {"route": "37", "longitude": -122.44578, "d_time": -130, "time": 37440, "latitude": 37.75041, "trip": " 8514", "size": 10}, {"d_time": -130, "time": 38040, "latitude": 37.75041, "route": "37", "trip": " 8514", "longitude": -122.44578, "size": 0}], [{"d_time": 230, "time": 35220, "latitude": 37.76767, "route": "37", "trip": " 8517", "longitude": -122.42913, "size": 0}, {"route": "37", "longitude": -122.42913, "d_time": 230, "time": 35220, "latitude": 37.76767, "trip": " 8517", "size": 10}, {"route": "37", "longitude": -122.43538, "d_time": 170, "time": 35460, "latitude": 37.76262, "trip": " 8517", "size": 10}, {"route": "37", "longitude": -122.444766, "d_time": 199, "time": 35940, "latitude": 37.747042, "trip": " 8517", "size": 10}, {"route": "37", "longitude": -122.445407, "d_time": 79, "time": 34380, "latitude": 37.770089, "trip": " 8517", "size": 10}, {"route": "37", "longitude": -122.44578, "d_time": 217, "time": 36240, "latitude": 37.75041, "trip": " 8517", "size": 10}, {"d_time": 217, "time": 36840, "latitude": 37.75041, "route": "37", "trip": " 8517", "longitude": -122.44578, "size": 0}], [{"d_time": 233, "time": 34140, "latitude": 37.76767, "route": "37", "trip": " 8512", "longitude": -122.42913, "size": 0}, {"route": "37", "longitude": -122.42913, "d_time": 233, "time": 34140, "latitude": 37.76767, "trip": " 8512", "size": 10}, {"route": "37", "longitude": -122.43538, "d_time": 184, "time": 34380, "latitude": 37.76262, "trip": " 8512", "size": 10}, {"route": "37", "longitude": -122.444766, "d_time": 212, "time": 34860, "latitude": 37.747042, "trip": " 8512", "size": 10}, {"route": "37", "longitude": -122.445407, "d_time": 117, "time": 33300, "latitude": 37.770089, "trip": " 8512", "size": 10}, {"route": "37", "longitude": -122.44578, "d_time": 231, "time": 35160, "latitude": 37.75041, "trip": " 8512", "size": 10}, {"d_time": 231, "time": 35760, "latitude": 37.75041, "route": "37", "trip": " 8512", "longitude": -122.44578, "size": 0}], [{"d_time": 0, "time": 32940, "latitude": 37.770089, "route": "37", "trip": " 8525", "longitude": -122.445407, "size": 0}, {"route": "37", "longitude": -122.445407, "d_time": 0, "time": 32940, "latitude": 37.770089, "trip": " 8525", "size": 10}, {"route": "37", "longitude": -122.445407, "d_time": 0, "time": 33180, "latitude": 37.770089, "trip": " 8525", "size": 10}, {"route": "37", "longitude": -122.445407, "d_time": 0, "time": 33660, "latitude": 37.770089, "trip": " 8525", "size": 10}, {"route": "37", "longitude": -122.445407, "d_time": 431, "time": 32100, "latitude": 37.770089, "trip": " 8525", "size": 10}, {"d_time": 431, "time": 32700, "latitude": 37.770089, "route": "37", "trip": " 8525", "longitude": -122.445407, "size": 0}], [{"d_time": 0, "time": 33960, "latitude": 37.76767, "route": "37", "trip": " 8514", "longitude": -122.42913, "size": 0}, {"route": "37", "longitude": -122.42913, "d_time": 0, "time": 33960, "latitude": 37.76767, "trip": " 8514", "size": 10}, {"route": "37", "longitude": -122.42913, "d_time": 38, "time": 31740, "latitude": 37.76767, "trip": " 8514", "size": 10}, {"route": "37", "longitude": -122.43538, "d_time": -22, "time": 31980, "latitude": 37.76262, "trip": " 8514", "size": 10}, {"route": "37", "longitude": -122.444766, "d_time": -76, "time": 32460, "latitude": 37.747042, "trip": " 8514", "size": 10}, {"route": "37", "longitude": -122.445407, "d_time": -4, "time": 30900, "latitude": 37.770089, "trip": " 8514", "size": 10}, {"route": "37", "longitude": -122.44578, "d_time": 12, "time": 32760, "latitude": 37.75041, "trip": " 8514", "size": 10}, {"d_time": 12, "time": 33360, "latitude": 37.75041, "route": "37", "trip": " 8514", "longitude": -122.44578, "size": 0}], [{"d_time": 859, "time": 30540, "latitude": 37.76767, "route": "37", "trip": " 8517", "longitude": -122.42913, "size": 0}, {"route": "37", "longitude": -122.42913, "d_time": 859, "time": 30540, "latitude": 37.76767, "trip": " 8517", "size": 10}, {"route": "37", "longitude": -122.43538, "d_time": 818, "time": 30780, "latitude": 37.76262, "trip": " 8517", "size": 10}, {"route": "37", "longitude": -122.444766, "d_time": 961, "time": 31260, "latitude": 37.747042, "trip": " 8517", "size": 10}, {"route": "37", "longitude": -122.445407, "d_time": 702, "time": 29700, "latitude": 37.770089, "trip": " 8517", "size": 10}, {"route": "37", "longitude": -122.44578, "d_time": 1012, "time": 31560, "latitude": 37.75041, "trip": " 8517", "size": 10}, {"d_time": 1012, "time": 32160, "latitude": 37.75041, "route": "37", "trip": " 8517", "longitude": -122.44578, "size": 0}], [{"d_time": 806, "time": 29640, "latitude": 37.76767, "route": "37", "trip": " 8512", "longitude": -122.42913, "size": 0}, {"route": "37", "longitude": -122.42913, "d_time": 806, "time": 29640, "latitude": 37.76767, "trip": " 8512", "size": 10}, {"route": "37", "longitude": -122.43538, "d_time": 710, "time": 29880, "latitude": 37.76262, "trip": " 8512", "size": 10}, {"route": "37", "longitude": -122.444766, "d_time": 761, "time": 30360, "latitude": 37.747042, "trip": " 8512", "size": 10}, {"route": "37", "longitude": -122.445407, "d_time": 404, "time": 28800, "latitude": 37.770089, "trip": " 8512", "size": 10}, {"route": "37", "longitude": -122.44578, "d_time": 861, "time": 30660, "latitude": 37.75041, "trip": " 8512", "size": 10}, {"d_time": 861, "time": 31260, "latitude": 37.75041, "route": "37", "trip": " 8512", "longitude": -122.44578, "size": 0}], [{"d_time": 128, "time": 27840, "latitude": 37.76767, "route": "37", "trip": " 8525", "longitude": -122.42913, "size": 0}, {"route": "37", "longitude": -122.42913, "d_time": 128, "time": 27840, "latitude": 37.76767, "trip": " 8525", "size": 10}, {"route": "37", "longitude": -122.43538, "d_time": 78, "time": 28080, "latitude": 37.76262, "trip": " 8525", "size": 10}, {"route": "37", "longitude": -122.444766, "d_time": 84, "time": 28560, "latitude": 37.747042, "trip": " 8525", "size": 10}, {"route": "37", "longitude": -122.445407, "d_time": -22, "time": 27000, "latitude": 37.770089, "trip": " 8525", "size": 10}, {"route": "37", "longitude": -122.44578, "d_time": 73, "time": 28860, "latitude": 37.75041, "trip": " 8525", "size": 10}, {"d_time": 73, "time": 29460, "latitude": 37.75041, "route": "37", "trip": " 8525", "longitude": -122.44578, "size": 0}], [{"d_time": 31, "time": 26940, "latitude": 37.76767, "route": "37", "trip": " 8514", "longitude": -122.42913, "size": 0}, {"route": "37", "longitude": -122.42913, "d_time": 31, "time": 26940, "latitude": 37.76767, "trip": " 8514", "size": 10}, {"route": "37", "longitude": -122.43538, "d_time": -1, "time": 27180, "latitude": 37.76262, "trip": " 8514", "size": 10}, {"route": "37", "longitude": -122.444766, "d_time": 87, "time": 27660, "latitude": 37.747042, "trip": " 8514", "size": 10}, {"route": "37", "longitude": -122.445407, "d_time": -22, "time": 26100, "latitude": 37.770089, "trip": " 8514", "size": 10}, {"route": "37", "longitude": -122.44578, "d_time": 129, "time": 27960, "latitude": 37.75041, "trip": " 8514", "size": 10}, {"d_time": 129, "time": 28560, "latitude": 37.75041, "route": "37", "trip": " 8514", "longitude": -122.44578, "size": 0}], [{"d_time": 318, "time": 26040, "latitude": 37.76767, "route": "37", "trip": " 8517", "longitude": -122.42913, "size": 0}, {"route": "37", "longitude": -122.42913, "d_time": 318, "time": 26040, "latitude": 37.76767, "trip": " 8517", "size": 10}, {"route": "37", "longitude": -122.43538, "d_time": 277, "time": 26280, "latitude": 37.76262, "trip": " 8517", "size": 10}, {"route": "37", "longitude": -122.444766, "d_time": 392, "time": 26760, "latitude": 37.747042, "trip": " 8517", "size": 10}, {"route": "37", "longitude": -122.445407, "d_time": 356, "time": 25200, "latitude": 37.770089, "trip": " 8517", "size": 10}, {"route": "37", "longitude": -122.44578, "d_time": 575, "time": 27060, "latitude": 37.75041, "trip": " 8517", "size": 10}, {"d_time": 575, "time": 27660, "latitude": 37.75041, "route": "37", "trip": " 8517", "longitude": -122.44578, "size": 0}], [{"d_time": 21, "time": 25140, "latitude": 37.76767, "route": "37", "trip": " 8512", "longitude": -122.42913, "size": 0}, {"route": "37", "longitude": -122.42913, "d_time": 21, "time": 25140, "latitude": 37.76767, "trip": " 8512", "size": 10}, {"route": "37", "longitude": -122.43538, "d_time": -5, "time": 25380, "latitude": 37.76262, "trip": " 8512", "size": 10}, {"route": "37", "longitude": -122.444766, "d_time": 0, "time": 25860, "latitude": 37.747042, "trip": " 8512", "size": 10}, {"route": "37", "longitude": -122.445407, "d_time": 50, "time": 24300, "latitude": 37.770089, "trip": " 8512", "size": 10}, {"route": "37", "longitude": -122.44578, "d_time": -4, "time": 26160, "latitude": 37.75041, "trip": " 8512", "size": 10}, {"d_time": -4, "time": 26760, "latitude": 37.75041, "route": "37", "trip": " 8512", "longitude": -122.44578, "size": 0}], [{"d_time": 50, "time": 23340, "latitude": 37.76767, "route": "37", "trip": " 8525", "longitude": -122.42913, "size": 0}, {"route": "37", "longitude": -122.42913, "d_time": 50, "time": 23340, "latitude": 37.76767, "trip": " 8525", "size": 10}, {"route": "37", "longitude": -122.43538, "d_time": -4, "time": 23580, "latitude": 37.76262, "trip": " 8525", "size": 10}, {"route": "37", "longitude": -122.444766, "d_time": -41, "time": 24060, "latitude": 37.747042, "trip": " 8525", "size": 10}, {"route": "37", "longitude": -122.44578, "d_time": -41, "time": 22500, "latitude": 37.75041, "trip": " 8525", "size": 10}, {"route": "37", "longitude": -122.44578, "d_time": -59, "time": 24360, "latitude": 37.75041, "trip": " 8525", "size": 10}, {"d_time": -59, "time": 24960, "latitude": 37.75041, "route": "37", "trip": " 8525", "longitude": -122.44578, "size": 0}], [{"d_time": 0, "time": 23100, "latitude": 37.75041, "route": "37", "trip": " 8512", "longitude": -122.44578, "size": 0}, {"route": "37", "longitude": -122.44578, "d_time": 0, "time": 23100, "latitude": 37.75041, "trip": " 8512", "size": 10}, {"route": "37", "longitude": -122.44578, "d_time": 0, "time": 23460, "latitude": 37.75041, "trip": " 8512", "size": 10}, {"route": "37", "longitude": -122.44578, "d_time": 0, "time": 22200, "latitude": 37.75041, "trip": " 8512", "size": 10}, {"route": "37", "longitude": -122.44578, "d_time": -35, "time": 22560, "latitude": 37.75041, "trip": " 8512", "size": 10}, {"d_time": -35, "time": 23160, "latitude": 37.75041, "route": "37", "trip": " 8512", "longitude": -122.44578, "size": 0}], [{"d_time": 293, "time": 28740, "latitude": 37.76767, "route": "37", "trip": " 8524", "longitude": -122.42913, "size": 0}, {"route": "37", "longitude": -122.42913, "d_time": 293, "time": 28740, "latitude": 37.76767, "trip": " 8524", "size": 10}, {"route": "37", "longitude": -122.43538, "d_time": 351, "time": 28980, "latitude": 37.76262, "trip": " 8524", "size": 10}, {"route": "37", "longitude": -122.444766, "d_time": 357, "time": 29460, "latitude": 37.747042, "trip": " 8524", "size": 10}, {"route": "37", "longitude": -122.445407, "d_time": 261, "time": 27900, "latitude": 37.770089, "trip": " 8524", "size": 10}, {"route": "37", "longitude": -122.42913, "d_time": 0, "time": 29760, "latitude": 37.76767, "trip": " 8524", "size": 10}, {"d_time": 0, "time": 30360, "latitude": 37.76767, "route": "37", "trip": " 8524", "longitude": -122.42913, "size": 0}], [{"d_time": -137, "time": 24240, "latitude": 37.76767, "route": "37", "trip": " 8524", "longitude": -122.42913, "size": 0}, {"route": "37", "longitude": -122.42913, "d_time": -137, "time": 24240, "latitude": 37.76767, "trip": " 8524", "size": 10}, {"route": "37", "longitude": -122.43538, "d_time": -198, "time": 24480, "latitude": 37.76262, "trip": " 8524", "size": 10}, {"route": "37", "longitude": -122.444766, "d_time": -217, "time": 24960, "latitude": 37.747042, "trip": " 8524", "size": 10}, {"route": "37", "longitude": -122.445407, "d_time": 51, "time": 23400, "latitude": 37.770089, "trip": " 8524", "size": 10}, {"route": "37", "longitude": -122.44578, "d_time": -247, "time": 25260, "latitude": 37.75041, "trip": " 8524", "size": 10}, {"d_time": -247, "time": 25860, "latitude": 37.75041, "route": "37", "trip": " 8524", "longitude": -122.44578, "size": 0}], [{"d_time": 72, "time": 67620, "latitude": 37.76767, "route": "37", "trip": " 8512", "longitude": -122.42913, "size": 0}, {"route": "37", "longitude": -122.42913, "d_time": 72, "time": 67620, "latitude": 37.76767, "trip": " 8512", "size": 10}, {"route": "37", "longitude": -122.43538, "d_time": 9, "time": 67860, "latitude": 37.76262, "trip": " 8512", "size": 10}, {"route": "37", "longitude": -122.444766, "d_time": 183, "time": 68340, "latitude": 37.747042, "trip": " 8512", "size": 10}, {"route": "37", "longitude": -122.44578, "d_time": 183, "time": 66780, "latitude": 37.75041, "trip": " 8512", "size": 10}, {"route": "37", "longitude": -122.44578, "d_time": 266, "time": 68640, "latitude": 37.75041, "trip": " 8512", "size": 10}, {"d_time": 266, "time": 69240, "latitude": 37.75041, "route": "37", "trip": " 8512", "longitude": -122.44578, "size": 0}], [{"d_time": 268, "time": 84600, "latitude": 37.767768, "route": "37", "trip": " 8525", "longitude": -122.429088, "size": 0}, {"route": "37", "longitude": -122.429088, "d_time": 268, "time": 84600, "latitude": 37.767768, "trip": " 8525", "size": 10}, {"route": "37", "longitude": -122.435449, "d_time": 254, "time": 84360, "latitude": 37.76246, "trip": " 8525", "size": 10}, {"route": "37", "longitude": -122.4442, "d_time": 60, "time": 84000, "latitude": 37.74715, "trip": " 8525", "size": 10}, {"route": "37", "longitude": -122.445407, "d_time": 274, "time": 85380, "latitude": 37.770089, "trip": " 8525", "size": 10}, {"route": "37", "longitude": -122.44578, "d_time": 69, "time": 83880, "latitude": 37.75041, "trip": " 8525", "size": 10}, {"d_time": 69, "time": 84480, "latitude": 37.75041, "route": "37", "trip": " 8525", "longitude": -122.44578, "size": 0}], [{"d_time": 181, "time": 82800, "latitude": 37.767768, "route": "37", "trip": " 8517", "longitude": -122.429088, "size": 0}, {"route": "37", "longitude": -122.429088, "d_time": 181, "time": 82800, "latitude": 37.767768, "trip": " 8517", "size": 10}, {"route": "37", "longitude": -122.435449, "d_time": 151, "time": 82560, "latitude": 37.76246, "trip": " 8517", "size": 10}, {"route": "37", "longitude": -122.4442, "d_time": 61, "time": 82200, "latitude": 37.74715, "trip": " 8517", "size": 10}, {"route": "37", "longitude": -122.445407, "d_time": 187, "time": 83580, "latitude": 37.770089, "trip": " 8517", "size": 10}, {"route": "37", "longitude": -122.44578, "d_time": 65, "time": 82080, "latitude": 37.75041, "trip": " 8517", "size": 10}, {"d_time": 65, "time": 82680, "latitude": 37.75041, "route": "37", "trip": " 8517", "longitude": -122.44578, "size": 0}], [{"d_time": 263, "time": 81000, "latitude": 37.767768, "route": "37", "trip": " 8512", "longitude": -122.429088, "size": 0}, {"route": "37", "longitude": -122.429088, "d_time": 263, "time": 81000, "latitude": 37.767768, "trip": " 8512", "size": 10}, {"route": "37", "longitude": -122.435449, "d_time": 143, "time": 80760, "latitude": 37.76246, "trip": " 8512", "size": 10}, {"route": "37", "longitude": -122.4442, "d_time": 60, "time": 80400, "latitude": 37.74715, "trip": " 8512", "size": 10}, {"route": "37", "longitude": -122.445407, "d_time": 291, "time": 81780, "latitude": 37.770089, "trip": " 8512", "size": 10}, {"route": "37", "longitude": -122.44578, "d_time": 37, "time": 80280, "latitude": 37.75041, "trip": " 8512", "size": 10}, {"d_time": 37, "time": 80880, "latitude": 37.75041, "route": "37", "trip": " 8512", "longitude": -122.44578, "size": 0}], [{"d_time": 357, "time": 79200, "latitude": 37.767768, "route": "37", "trip": " 8525", "longitude": -122.429088, "size": 0}, {"route": "37", "longitude": -122.429088, "d_time": 357, "time": 79200, "latitude": 37.767768, "trip": " 8525", "size": 10}, {"route": "37", "longitude": -122.435449, "d_time": 330, "time": 78960, "latitude": 37.76246, "trip": " 8525", "size": 10}, {"route": "37", "longitude": -122.4442, "d_time": 57, "time": 78600, "latitude": 37.74715, "trip": " 8525", "size": 10}, {"route": "37", "longitude": -122.445407, "d_time": 454, "time": 79980, "latitude": 37.770089, "trip": " 8525", "size": 10}, {"route": "37", "longitude": -122.44578, "d_time": 42, "time": 78480, "latitude": 37.75041, "trip": " 8525", "size": 10}, {"d_time": 42, "time": 79080, "latitude": 37.75041, "route": "37", "trip": " 8525", "longitude": -122.44578, "size": 0}], [{"d_time": 151, "time": 77400, "latitude": 37.767768, "route": "37", "trip": " 8517", "longitude": -122.429088, "size": 0}, {"route": "37", "longitude": -122.429088, "d_time": 151, "time": 77400, "latitude": 37.767768, "trip": " 8517", "size": 10}, {"route": "37", "longitude": -122.435449, "d_time": 166, "time": 77160, "latitude": 37.76246, "trip": " 8517", "size": 10}, {"route": "37", "longitude": -122.4442, "d_time": 45, "time": 76800, "latitude": 37.74715, "trip": " 8517", "size": 10}, {"route": "37", "longitude": -122.445407, "d_time": 329, "time": 78180, "latitude": 37.770089, "trip": " 8517", "size": 10}, {"route": "37", "longitude": -122.44578, "d_time": 84, "time": 76680, "latitude": 37.75041, "trip": " 8517", "size": 10}, {"d_time": 84, "time": 77280, "latitude": 37.75041, "route": "37", "trip": " 8517", "longitude": -122.44578, "size": 0}], [{"d_time": 0, "time": 75600, "latitude": 37.767768, "route": "37", "trip": " 8512", "longitude": -122.429088, "size": 0}, {"route": "37", "longitude": -122.429088, "d_time": 0, "time": 75600, "latitude": 37.767768, "trip": " 8512", "size": 10}, {"route": "37", "longitude": -122.435449, "d_time": 57, "time": 75360, "latitude": 37.76246, "trip": " 8512", "size": 10}, {"route": "37", "longitude": -122.4442, "d_time": -30, "time": 75000, "latitude": 37.74715, "trip": " 8512", "size": 10}, {"route": "37", "longitude": -122.445407, "d_time": 4, "time": 76380, "latitude": 37.770089, "trip": " 8512", "size": 10}, {"route": "37", "longitude": -122.44578, "d_time": 3, "time": 74880, "latitude": 37.75041, "trip": " 8512", "size": 10}, {"d_time": 3, "time": 75480, "latitude": 37.75041, "route": "37", "trip": " 8512", "longitude": -122.44578, "size": 0}], [{"d_time": 511, "time": 73800, "latitude": 37.767768, "route": "37", "trip": " 8525", "longitude": -122.429088, "size": 0}, {"route": "37", "longitude": -122.429088, "d_time": 511, "time": 73800, "latitude": 37.767768, "trip": " 8525", "size": 10}, {"route": "37", "longitude": -122.435449, "d_time": 516, "time": 73560, "latitude": 37.76246, "trip": " 8525", "size": 10}, {"route": "37", "longitude": -122.4442, "d_time": 331, "time": 73200, "latitude": 37.74715, "trip": " 8525", "size": 10}, {"route": "37", "longitude": -122.445407, "d_time": 634, "time": 74580, "latitude": 37.770089, "trip": " 8525", "size": 10}, {"route": "37", "longitude": -122.44578, "d_time": 297, "time": 73080, "latitude": 37.75041, "trip": " 8525", "size": 10}, {"d_time": 297, "time": 73680, "latitude": 37.75041, "route": "37", "trip": " 8525", "longitude": -122.44578, "size": 0}], [{"d_time": 373, "time": 72000, "latitude": 37.767768, "route": "37", "trip": " 8517", "longitude": -122.429088, "size": 0}, {"route": "37", "longitude": -122.429088, "d_time": 373, "time": 72000, "latitude": 37.767768, "trip": " 8517", "size": 10}, {"route": "37", "longitude": -122.435449, "d_time": 268, "time": 71760, "latitude": 37.76246, "trip": " 8517", "size": 10}, {"route": "37", "longitude": -122.4442, "d_time": 63, "time": 71400, "latitude": 37.74715, "trip": " 8517", "size": 10}, {"route": "37", "longitude": -122.445407, "d_time": 508, "time": 72780, "latitude": 37.770089, "trip": " 8517", "size": 10}, {"route": "37", "longitude": -122.44578, "d_time": 35, "time": 71280, "latitude": 37.75041, "trip": " 8517", "size": 10}, {"d_time": 35, "time": 71880, "latitude": 37.75041, "route": "37", "trip": " 8517", "longitude": -122.44578, "size": 0}], [{"d_time": 194, "time": 70200, "latitude": 37.767768, "route": "37", "trip": " 8512", "longitude": -122.429088, "size": 0}, {"route": "37", "longitude": -122.429088, "d_time": 194, "time": 70200, "latitude": 37.767768, "trip": " 8512", "size": 10}, {"route": "37", "longitude": -122.435449, "d_time": 164, "time": 69960, "latitude": 37.76246, "trip": " 8512", "size": 10}, {"route": "37", "longitude": -122.4442, "d_time": -65, "time": 69600, "latitude": 37.74715, "trip": " 8512", "size": 10}, {"route": "37", "longitude": -122.445407, "d_time": 259, "time": 70980, "latitude": 37.770089, "trip": " 8512", "size": 10}, {"route": "37", "longitude": -122.44578, "d_time": -8, "time": 69480, "latitude": 37.75041, "trip": " 8512", "size": 10}, {"d_time": -8, "time": 70080, "latitude": 37.75041, "route": "37", "trip": " 8512", "longitude": -122.44578, "size": 0}], [{"d_time": 413, "time": 68880, "latitude": 37.767768, "route": "37", "trip": " 8525", "longitude": -122.429088, "size": 0}, {"route": "37", "longitude": -122.429088, "d_time": 413, "time": 68880, "latitude": 37.767768, "trip": " 8525", "size": 10}, {"route": "37", "longitude": -122.435449, "d_time": 288, "time": 68640, "latitude": 37.76246, "trip": " 8525", "size": 10}, {"route": "37", "longitude": -122.4442, "d_time": 26, "time": 68280, "latitude": 37.74715, "trip": " 8525", "size": 10}, {"route": "37", "longitude": -122.445407, "d_time": 591, "time": 69660, "latitude": 37.770089, "trip": " 8525", "size": 10}, {"route": "37", "longitude": -122.44578, "d_time": 16, "time": 68160, "latitude": 37.75041, "trip": " 8525", "size": 10}, {"d_time": 16, "time": 68760, "latitude": 37.75041, "route": "37", "trip": " 8525", "longitude": -122.44578, "size": 0}], [{"d_time": 69, "time": 66600, "latitude": 37.767768, "route": "37", "trip": " 8517", "longitude": -122.429088, "size": 0}, {"route": "37", "longitude": -122.429088, "d_time": 69, "time": 66600, "latitude": 37.767768, "trip": " 8517", "size": 10}, {"route": "37", "longitude": -122.435449, "d_time": 63, "time": 66300, "latitude": 37.76246, "trip": " 8517", "size": 10}, {"route": "37", "longitude": -122.4442, "d_time": 22, "time": 65880, "latitude": 37.74715, "trip": " 8517", "size": 10}, {"route": "37", "longitude": -122.445407, "d_time": 189, "time": 67380, "latitude": 37.770089, "trip": " 8517", "size": 10}, {"route": "37", "longitude": -122.44578, "d_time": 49, "time": 65760, "latitude": 37.75041, "trip": " 8517", "size": 10}, {"d_time": 49, "time": 66360, "latitude": 37.75041, "route": "37", "trip": " 8517", "longitude": -122.44578, "size": 0}], [{"d_time": 163, "time": 65400, "latitude": 37.767768, "route": "37", "trip": " 8512", "longitude": -122.429088, "size": 0}, {"route": "37", "longitude": -122.429088, "d_time": 163, "time": 65400, "latitude": 37.767768, "trip": " 8512", "size": 10}, {"route": "37", "longitude": -122.435449, "d_time": 73, "time": 65100, "latitude": 37.76246, "trip": " 8512", "size": 10}, {"route": "37", "longitude": -122.4442, "d_time": -84, "time": 64680, "latitude": 37.74715, "trip": " 8512", "size": 10}, {"route": "37", "longitude": -122.44578, "d_time": -84, "time": 66180, "latitude": 37.75041, "trip": " 8512", "size": 10}, {"route": "37", "longitude": -122.44578, "d_time": -23, "time": 64560, "latitude": 37.75041, "trip": " 8512", "size": 10}, {"d_time": -23, "time": 65160, "latitude": 37.75041, "route": "37", "trip": " 8512", "longitude": -122.44578, "size": 0}], [{"d_time": 114, "time": 64200, "latitude": 37.767768, "route": "37", "trip": " 8525", "longitude": -122.429088, "size": 0}, {"route": "37", "longitude": -122.429088, "d_time": 114, "time": 64200, "latitude": 37.767768, "trip": " 8525", "size": 10}, {"route": "37", "longitude": -122.435449, "d_time": 103, "time": 63900, "latitude": 37.76246, "trip": " 8525", "size": 10}, {"route": "37", "longitude": -122.4442, "d_time": -55, "time": 63480, "latitude": 37.74715, "trip": " 8525", "size": 10}, {"route": "37", "longitude": -122.445407, "d_time": 307, "time": 64980, "latitude": 37.770089, "trip": " 8525", "size": 10}, {"route": "37", "longitude": -122.44578, "d_time": -18, "time": 63360, "latitude": 37.75041, "trip": " 8525", "size": 10}, {"d_time": -18, "time": 63960, "latitude": 37.75041, "route": "37", "trip": " 8525", "longitude": -122.44578, "size": 0}], [{"d_time": 225, "time": 63000, "latitude": 37.767768, "route": "37", "trip": " 8514", "longitude": -122.429088, "size": 0}, {"route": "37", "longitude": -122.429088, "d_time": 225, "time": 63000, "latitude": 37.767768, "trip": " 8514", "size": 10}, {"route": "37", "longitude": -122.435449, "d_time": 175, "time": 62700, "latitude": 37.76246, "trip": " 8514", "size": 10}, {"route": "37", "longitude": -122.4442, "d_time": 83, "time": 62280, "latitude": 37.74715, "trip": " 8514", "size": 10}, {"route": "37", "longitude": -122.445407, "d_time": 353, "time": 63780, "latitude": 37.770089, "trip": " 8514", "size": 10}, {"route": "37", "longitude": -122.44578, "d_time": 10, "time": 62160, "latitude": 37.75041, "trip": " 8514", "size": 10}, {"d_time": 10, "time": 62760, "latitude": 37.75041, "route": "37", "trip": " 8514", "longitude": -122.44578, "size": 0}], [{"d_time": 156, "time": 61800, "latitude": 37.767768, "route": "37", "trip": " 8517", "longitude": -122.429088, "size": 0}, {"route": "37", "longitude": -122.429088, "d_time": 156, "time": 61800, "latitude": 37.767768, "trip": " 8517", "size": 10}, {"route": "37", "longitude": -122.435449, "d_time": 166, "time": 61500, "latitude": 37.76246, "trip": " 8517", "size": 10}, {"route": "37", "longitude": -122.4442, "d_time": 49, "time": 61080, "latitude": 37.74715, "trip": " 8517", "size": 10}, {"route": "37", "longitude": -122.445407, "d_time": 339, "time": 62580, "latitude": 37.770089, "trip": " 8517", "size": 10}, {"route": "37", "longitude": -122.44578, "d_time": 79, "time": 60960, "latitude": 37.75041, "trip": " 8517", "size": 10}, {"d_time": 79, "time": 61560, "latitude": 37.75041, "route": "37", "trip": " 8517", "longitude": -122.44578, "size": 0}], [{"d_time": 35, "time": 60600, "latitude": 37.767768, "route": "37", "trip": " 8512", "longitude": -122.429088, "size": 0}, {"route": "37", "longitude": -122.429088, "d_time": 35, "time": 60600, "latitude": 37.767768, "trip": " 8512", "size": 10}, {"route": "37", "longitude": -122.435449, "d_time": 14, "time": 60300, "latitude": 37.76246, "trip": " 8512", "size": 10}, {"route": "37", "longitude": -122.4442, "d_time": -30, "time": 59880, "latitude": 37.74715, "trip": " 8512", "size": 10}, {"route": "37", "longitude": -122.445407, "d_time": 175, "time": 61380, "latitude": 37.770089, "trip": " 8512", "size": 10}, {"route": "37", "longitude": -122.44578, "d_time": 14, "time": 59760, "latitude": 37.75041, "trip": " 8512", "size": 10}, {"d_time": 14, "time": 60360, "latitude": 37.75041, "route": "37", "trip": " 8512", "longitude": -122.44578, "size": 0}], [{"d_time": 233, "time": 59400, "latitude": 37.767768, "route": "37", "trip": " 8525", "longitude": -122.429088, "size": 0}, {"route": "37", "longitude": -122.429088, "d_time": 233, "time": 59400, "latitude": 37.767768, "trip": " 8525", "size": 10}, {"route": "37", "longitude": -122.435449, "d_time": 242, "time": 59100, "latitude": 37.76246, "trip": " 8525", "size": 10}, {"route": "37", "longitude": -122.4442, "d_time": 75, "time": 58680, "latitude": 37.74715, "trip": " 8525", "size": 10}, {"route": "37", "longitude": -122.445407, "d_time": 437, "time": 60180, "latitude": 37.770089, "trip": " 8525", "size": 10}, {"route": "37", "longitude": -122.44578, "d_time": 53, "time": 58560, "latitude": 37.75041, "trip": " 8525", "size": 10}, {"d_time": 53, "time": 59160, "latitude": 37.75041, "route": "37", "trip": " 8525", "longitude": -122.44578, "size": 0}], [{"d_time": 154, "time": 58200, "latitude": 37.767768, "route": "37", "trip": " 8514", "longitude": -122.429088, "size": 0}, {"route": "37", "longitude": -122.429088, "d_time": 154, "time": 58200, "latitude": 37.767768, "trip": " 8514", "size": 10}, {"route": "37", "longitude": -122.435449, "d_time": 158, "time": 57900, "latitude": 37.76246, "trip": " 8514", "size": 10}, {"route": "37", "longitude": -122.4442, "d_time": 38, "time": 57480, "latitude": 37.74715, "trip": " 8514", "size": 10}, {"route": "37", "longitude": -122.445407, "d_time": 283, "time": 58980, "latitude": 37.770089, "trip": " 8514", "size": 10}, {"route": "37", "longitude": -122.44578, "d_time": 23, "time": 57360, "latitude": 37.75041, "trip": " 8514", "size": 10}, {"d_time": 23, "time": 57960, "latitude": 37.75041, "route": "37", "trip": " 8514", "longitude": -122.44578, "size": 0}], [{"d_time": 22, "time": 57000, "latitude": 37.767768, "route": "37", "trip": " 8517", "longitude": -122.429088, "size": 0}, {"route": "37", "longitude": -122.429088, "d_time": 22, "time": 57000, "latitude": 37.767768, "trip": " 8517", "size": 10}, {"route": "37", "longitude": -122.435449, "d_time": 125, "time": 56700, "latitude": 37.76246, "trip": " 8517", "size": 10}, {"route": "37", "longitude": -122.4442, "d_time": -31, "time": 56280, "latitude": 37.74715, "trip": " 8517", "size": 10}, {"route": "37", "longitude": -122.445407, "d_time": 38, "time": 57780, "latitude": 37.770089, "trip": " 8517", "size": 10}, {"route": "37", "longitude": -122.44578, "d_time": 51, "time": 56160, "latitude": 37.75041, "trip": " 8517", "size": 10}, {"d_time": 51, "time": 56760, "latitude": 37.75041, "route": "37", "trip": " 8517", "longitude": -122.44578, "size": 0}], [{"d_time": 149, "time": 55800, "latitude": 37.767768, "route": "37", "trip": " 8512", "longitude": -122.429088, "size": 0}, {"route": "37", "longitude": -122.429088, "d_time": 149, "time": 55800, "latitude": 37.767768, "trip": " 8512", "size": 10}, {"route": "37", "longitude": -122.435449, "d_time": 133, "time": 55500, "latitude": 37.76246, "trip": " 8512", "size": 10}, {"route": "37", "longitude": -122.4442, "d_time": 13, "time": 55080, "latitude": 37.74715, "trip": " 8512", "size": 10}, {"route": "37", "longitude": -122.445407, "d_time": 265, "time": 56580, "latitude": 37.770089, "trip": " 8512", "size": 10}, {"route": "37", "longitude": -122.44578, "d_time": 37, "time": 54960, "latitude": 37.75041, "trip": " 8512", "size": 10}, {"d_time": 37, "time": 55560, "latitude": 37.75041, "route": "37", "trip": " 8512", "longitude": -122.44578, "size": 0}], [{"d_time": 449, "time": 54600, "latitude": 37.767768, "route": "37", "trip": " 8525", "longitude": -122.429088, "size": 0}, {"route": "37", "longitude": -122.429088, "d_time": 449, "time": 54600, "latitude": 37.767768, "trip": " 8525", "size": 10}, {"route": "37", "longitude": -122.435449, "d_time": 441, "time": 54300, "latitude": 37.76246, "trip": " 8525", "size": 10}, {"route": "37", "longitude": -122.4442, "d_time": 299, "time": 53880, "latitude": 37.74715, "trip": " 8525", "size": 10}, {"route": "37", "longitude": -122.445407, "d_time": 582, "time": 55380, "latitude": 37.770089, "trip": " 8525", "size": 10}, {"route": "37", "longitude": -122.44578, "d_time": 348, "time": 53760, "latitude": 37.75041, "trip": " 8525", "size": 10}, {"d_time": 348, "time": 54360, "latitude": 37.75041, "route": "37", "trip": " 8525", "longitude": -122.44578, "size": 0}], [{"d_time": 36, "time": 53400, "latitude": 37.767768, "route": "37", "trip": " 8514", "longitude": -122.429088, "size": 0}, {"route": "37", "longitude": -122.429088, "d_time": 36, "time": 53400, "latitude": 37.767768, "trip": " 8514", "size": 10}, {"route": "37", "longitude": -122.435449, "d_time": 98, "time": 53100, "latitude": 37.76246, "trip": " 8514", "size": 10}, {"route": "37", "longitude": -122.4442, "d_time": -22, "time": 52680, "latitude": 37.74715, "trip": " 8514", "size": 10}, {"route": "37", "longitude": -122.445407, "d_time": 84, "time": 54180, "latitude": 37.770089, "trip": " 8514", "size": 10}, {"route": "37", "longitude": -122.44578, "d_time": -2, "time": 52560, "latitude": 37.75041, "trip": " 8514", "size": 10}, {"d_time": -2, "time": 53160, "latitude": 37.75041, "route": "37", "trip": " 8514", "longitude": -122.44578, "size": 0}], [{"d_time": 104, "time": 52200, "latitude": 37.767768, "route": "37", "trip": " 8517", "longitude": -122.429088, "size": 0}, {"route": "37", "longitude": -122.429088, "d_time": 104, "time": 52200, "latitude": 37.767768, "trip": " 8517", "size": 10}, {"route": "37", "longitude": -122.435449, "d_time": 44, "time": 51900, "latitude": 37.76246, "trip": " 8517", "size": 10}, {"route": "37", "longitude": -122.4442, "d_time": -77, "time": 51480, "latitude": 37.74715, "trip": " 8517", "size": 10}, {"route": "37", "longitude": -122.445407, "d_time": 202, "time": 52980, "latitude": 37.770089, "trip": " 8517", "size": 10}, {"route": "37", "longitude": -122.44578, "d_time": -41, "time": 51360, "latitude": 37.75041, "trip": " 8517", "size": 10}, {"d_time": -41, "time": 51960, "latitude": 37.75041, "route": "37", "trip": " 8517", "longitude": -122.44578, "size": 0}], [{"d_time": 248, "time": 51000, "latitude": 37.767768, "route": "37", "trip": " 8512", "longitude": -122.429088, "size": 0}, {"route": "37", "longitude": -122.429088, "d_time": 248, "time": 51000, "latitude": 37.767768, "trip": " 8512", "size": 10}, {"route": "37", "longitude": -122.435449, "d_time": 158, "time": 50700, "latitude": 37.76246, "trip": " 8512", "size": 10}, {"route": "37", "longitude": -122.4442, "d_time": -77, "time": 50280, "latitude": 37.74715, "trip": " 8512", "size": 10}, {"route": "37", "longitude": -122.445407, "d_time": 319, "time": 51780, "latitude": 37.770089, "trip": " 8512", "size": 10}, {"route": "37", "longitude": -122.44578, "d_time": -12, "time": 50160, "latitude": 37.75041, "trip": " 8512", "size": 10}, {"d_time": -12, "time": 50760, "latitude": 37.75041, "route": "37", "trip": " 8512", "longitude": -122.44578, "size": 0}], [{"d_time": 516, "time": 49800, "latitude": 37.767768, "route": "37", "trip": " 8525", "longitude": -122.429088, "size": 0}, {"route": "37", "longitude": -122.429088, "d_time": 516, "time": 49800, "latitude": 37.767768, "trip": " 8525", "size": 10}, {"route": "37", "longitude": -122.435449, "d_time": 420, "time": 49500, "latitude": 37.76246, "trip": " 8525", "size": 10}, {"route": "37", "longitude": -122.4442, "d_time": 155, "time": 49080, "latitude": 37.74715, "trip": " 8525", "size": 10}, {"route": "37", "longitude": -122.445407, "d_time": 1082, "time": 50580, "latitude": 37.770089, "trip": " 8525", "size": 10}, {"route": "37", "longitude": -122.44578, "d_time": 168, "time": 48960, "latitude": 37.75041, "trip": " 8525", "size": 10}, {"d_time": 168, "time": 49560, "latitude": 37.75041, "route": "37", "trip": " 8525", "longitude": -122.44578, "size": 0}], [{"d_time": 175, "time": 48600, "latitude": 37.767768, "route": "37", "trip": " 8514", "longitude": -122.429088, "size": 0}, {"route": "37", "longitude": -122.429088, "d_time": 175, "time": 48600, "latitude": 37.767768, "trip": " 8514", "size": 10}, {"route": "37", "longitude": -122.435449, "d_time": 135, "time": 48300, "latitude": 37.76246, "trip": " 8514", "size": 10}, {"route": "37", "longitude": -122.4442, "d_time": -16, "time": 47880, "latitude": 37.74715, "trip": " 8514", "size": 10}, {"route": "37", "longitude": -122.445407, "d_time": 238, "time": 49380, "latitude": 37.770089, "trip": " 8514", "size": 10}, {"route": "37", "longitude": -122.44578, "d_time": -14, "time": 47760, "latitude": 37.75041, "trip": " 8514", "size": 10}, {"d_time": -14, "time": 48360, "latitude": 37.75041, "route": "37", "trip": " 8514", "longitude": -122.44578, "size": 0}], [{"d_time": 103, "time": 47400, "latitude": 37.767768, "route": "37", "trip": " 8517", "longitude": -122.429088, "size": 0}, {"route": "37", "longitude": -122.429088, "d_time": 103, "time": 47400, "latitude": 37.767768, "trip": " 8517", "size": 10}, {"route": "37", "longitude": -122.435449, "d_time": 180, "time": 47100, "latitude": 37.76246, "trip": " 8517", "size": 10}, {"d_time": 180, "time": 47700, "latitude": 37.76246, "route": "37", "trip": " 8517", "longitude": -122.435449, "size": 0}], [{"d_time": 28, "time": 89880, "latitude": 37.74715, "route": "37", "trip": " 8517", "longitude": -122.4442, "size": 0}, {"route": "37", "longitude": -122.4442, "d_time": 28, "time": 89880, "latitude": 37.74715, "trip": " 8517", "size": 10}, {"d_time": 28, "time": 90480, "latitude": 37.74715, "route": "37", "trip": " 8517", "longitude": -122.4442, "size": 0}], [{"d_time": 183, "time": 48180, "latitude": 37.770089, "route": "37", "trip": " 8517", "longitude": -122.445407, "size": 0}, {"route": "37", "longitude": -122.445407, "d_time": 183, "time": 48180, "latitude": 37.770089, "trip": " 8517", "size": 10}, {"d_time": 183, "time": 48780, "latitude": 37.770089, "route": "37", "trip": " 8517", "longitude": -122.445407, "size": 0}], [{"d_time": 60, "time": 89760, "latitude": 37.75041, "route": "37", "trip": " 8517", "longitude": -122.44578, "size": 0}, {"route": "37", "longitude": -122.44578, "d_time": 60, "time": 89760, "latitude": 37.75041, "trip": " 8517", "size": 10}, {"d_time": 60, "time": 90360, "latitude": 37.75041, "route": "37", "trip": " 8517", "longitude": -122.44578, "size": 0}], [{"d_time": -401, "time": 89400, "latitude": 37.767768, "route": "37", "trip": " 8512", "longitude": -122.429088, "size": 0}, {"route": "37", "longitude": -122.429088, "d_time": -401, "time": 89400, "latitude": 37.767768, "trip": " 8512", "size": 10}, {"route": "37", "longitude": -122.435449, "d_time": -379, "time": 89100, "latitude": 37.76246, "trip": " 8512", "size": 10}, {"route": "37", "longitude": -122.4442, "d_time": 6, "time": 88680, "latitude": 37.74715, "trip": " 8512", "size": 10}, {"d_time": 6, "time": 89280, "latitude": 37.74715, "route": "37", "trip": " 8512", "longitude": -122.4442, "size": 0}], [{"d_time": 42896, "time": 46980, "latitude": 37.770089, "route": "37", "trip": " 8512", "longitude": -122.445407, "size": 0}, {"route": "37", "longitude": -122.445407, "d_time": 42896, "time": 46980, "latitude": 37.770089, "trip": " 8512", "size": 10}, {"d_time": 42896, "time": 47580, "latitude": 37.770089, "route": "37", "trip": " 8512", "longitude": -122.445407, "size": 0}], [{"d_time": 126, "time": 88560, "latitude": 37.75041, "route": "37", "trip": " 8512", "longitude": -122.44578, "size": 0}, {"route": "37", "longitude": -122.44578, "d_time": 126, "time": 88560, "latitude": 37.75041, "trip": " 8512", "size": 10}, {"d_time": 126, "time": 89160, "latitude": 37.75041, "route": "37", "trip": " 8512", "longitude": -122.44578, "size": 0}], [{"d_time": 315, "time": 88200, "latitude": 37.767768, "route": "37", "trip": " 8525", "longitude": -122.429088, "size": 0}, {"route": "37", "longitude": -122.429088, "d_time": 315, "time": 88200, "latitude": 37.767768, "trip": " 8525", "size": 10}, {"route": "37", "longitude": -122.435449, "d_time": 304, "time": 87900, "latitude": 37.76246, "trip": " 8525", "size": 10}, {"route": "37", "longitude": -122.4442, "d_time": 18, "time": 87480, "latitude": 37.74715, "trip": " 8525", "size": 10}, {"route": "37", "longitude": -122.445407, "d_time": 692, "time": 88980, "latitude": 37.770089, "trip": " 8525", "size": 10}, {"route": "37", "longitude": -122.44578, "d_time": 3, "time": 87360, "latitude": 37.75041, "trip": " 8525", "size": 10}, {"d_time": 3, "time": 87960, "latitude": 37.75041, "route": "37", "trip": " 8525", "longitude": -122.44578, "size": 0}], [{"d_time": 87, "time": 87000, "latitude": 37.767768, "route": "37", "trip": " 8514", "longitude": -122.429088, "size": 0}, {"route": "37", "longitude": -122.429088, "d_time": 87, "time": 87000, "latitude": 37.767768, "trip": " 8514", "size": 10}, {"route": "37", "longitude": -122.435449, "d_time": 167, "time": 86700, "latitude": 37.76246, "trip": " 8514", "size": 10}, {"d_time": 167, "time": 87300, "latitude": 37.76246, "route": "37", "trip": " 8514", "longitude": -122.435449, "size": 0}], [{"d_time": 48, "time": 43080, "latitude": 37.74715, "route": "37", "trip": " 8514", "longitude": -122.4442, "size": 0}, {"route": "37", "longitude": -122.4442, "d_time": 48, "time": 43080, "latitude": 37.74715, "trip": " 8514", "size": 10}, {"d_time": 48, "time": 43680, "latitude": 37.74715, "route": "37", "trip": " 8514", "longitude": -122.4442, "size": 0}], [{"d_time": 235, "time": 87780, "latitude": 37.770089, "route": "37", "trip": " 8514", "longitude": -122.445407, "size": 0}, {"route": "37", "longitude": -122.445407, "d_time": 235, "time": 87780, "latitude": 37.770089, "trip": " 8514", "size": 10}, {"d_time": 235, "time": 88380, "latitude": 37.770089, "route": "37", "trip": " 8514", "longitude": -122.445407, "size": 0}], [{"d_time": 7, "time": 42960, "latitude": 37.75041, "route": "37", "trip": " 8514", "longitude": -122.44578, "size": 0}, {"route": "37", "longitude": -122.44578, "d_time": 7, "time": 42960, "latitude": 37.75041, "trip": " 8514", "size": 10}, {"d_time": 7, "time": 43560, "latitude": 37.75041, "route": "37", "trip": " 8514", "longitude": -122.44578, "size": 0}], [{"d_time": 130, "time": 42600, "latitude": 37.767768, "route": "37", "trip": " 8517", "longitude": -122.429088, "size": 0}, {"route": "37", "longitude": -122.429088, "d_time": 130, "time": 42600, "latitude": 37.767768, "trip": " 8517", "size": 10}, {"route": "37", "longitude": -122.435449, "d_time": 75, "time": 42300, "latitude": 37.76246, "trip": " 8517", "size": 10}, {"route": "37", "longitude": -122.4442, "d_time": -4, "time": 41880, "latitude": 37.74715, "trip": " 8517", "size": 10}, {"d_time": -4, "time": 42480, "latitude": 37.74715, "route": "37", "trip": " 8517", "longitude": -122.4442, "size": 0}], [{"d_time": 184, "time": 86580, "latitude": 37.770089, "route": "37", "trip": " 8517", "longitude": -122.445407, "size": 0}, {"route": "37", "longitude": -122.445407, "d_time": 184, "time": 86580, "latitude": 37.770089, "trip": " 8517", "size": 10}, {"d_time": 184, "time": 87180, "latitude": 37.770089, "route": "37", "trip": " 8517", "longitude": -122.445407, "size": 0}], [{"d_time": -32, "time": 41760, "latitude": 37.75041, "route": "37", "trip": " 8517", "longitude": -122.44578, "size": 0}, {"route": "37", "longitude": -122.44578, "d_time": -32, "time": 41760, "latitude": 37.75041, "trip": " 8517", "size": 10}, {"d_time": -32, "time": 42360, "latitude": 37.75041, "route": "37", "trip": " 8517", "longitude": -122.44578, "size": 0}], [{"d_time": 330, "time": 41400, "latitude": 37.767768, "route": "37", "trip": " 8512", "longitude": -122.429088, "size": 0}, {"route": "37", "longitude": -122.429088, "d_time": 330, "time": 41400, "latitude": 37.767768, "trip": " 8512", "size": 10}, {"route": "37", "longitude": -122.435449, "d_time": 232, "time": 41100, "latitude": 37.76246, "trip": " 8512", "size": 10}, {"route": "37", "longitude": -122.4442, "d_time": 22, "time": 40680, "latitude": 37.74715, "trip": " 8512", "size": 10}, {"route": "37", "longitude": -122.445407, "d_time": 566, "time": 42180, "latitude": 37.770089, "trip": " 8512", "size": 10}, {"route": "37", "longitude": -122.44578, "d_time": 11, "time": 40560, "latitude": 37.75041, "trip": " 8512", "size": 10}, {"d_time": 11, "time": 41160, "latitude": 37.75041, "route": "37", "trip": " 8512", "longitude": -122.44578, "size": 0}], [{"d_time": 103, "time": 40200, "latitude": 37.767768, "route": "37", "trip": " 8525", "longitude": -122.429088, "size": 0}, {"route": "37", "longitude": -122.429088, "d_time": 103, "time": 40200, "latitude": 37.767768, "trip": " 8525", "size": 10}, {"route": "37", "longitude": -122.435449, "d_time": 179, "time": 39900, "latitude": 37.76246, "trip": " 8525", "size": 10}, {"route": "37", "longitude": -122.4442, "d_time": -57, "time": 39480, "latitude": 37.74715, "trip": " 8525", "size": 10}, {"route": "37", "longitude": -122.445407, "d_time": 270, "time": 40980, "latitude": 37.770089, "trip": " 8525", "size": 10}, {"route": "37", "longitude": -122.44578, "d_time": -72, "time": 39360, "latitude": 37.75041, "trip": " 8525", "size": 10}, {"d_time": -72, "time": 39960, "latitude": 37.75041, "route": "37", "trip": " 8525", "longitude": -122.44578, "size": 0}], [{"d_time": 108, "time": 39000, "latitude": 37.767768, "route": "37", "trip": " 8514", "longitude": -122.429088, "size": 0}, {"route": "37", "longitude": -122.429088, "d_time": 108, "time": 39000, "latitude": 37.767768, "trip": " 8514", "size": 10}, {"route": "37", "longitude": -122.435449, "d_time": 103, "time": 38700, "latitude": 37.76246, "trip": " 8514", "size": 10}, {"route": "37", "longitude": -122.4442, "d_time": -17, "time": 38280, "latitude": 37.74715, "trip": " 8514", "size": 10}, {"route": "37", "longitude": -122.445407, "d_time": 130, "time": 39780, "latitude": 37.770089, "trip": " 8514", "size": 10}, {"route": "37", "longitude": -122.44578, "d_time": 13, "time": 38160, "latitude": 37.75041, "trip": " 8514", "size": 10}, {"d_time": 13, "time": 38760, "latitude": 37.75041, "route": "37", "trip": " 8514", "longitude": -122.44578, "size": 0}], [{"d_time": 144, "time": 37800, "latitude": 37.767768, "route": "37", "trip": " 8517", "longitude": -122.429088, "size": 0}, {"route": "37", "longitude": -122.429088, "d_time": 144, "time": 37800, "latitude": 37.767768, "trip": " 8517", "size": 10}, {"route": "37", "longitude": -122.435449, "d_time": 225, "time": 37500, "latitude": 37.76246, "trip": " 8517", "size": 10}, {"route": "37", "longitude": -122.4442, "d_time": 104, "time": 37080, "latitude": 37.74715, "trip": " 8517", "size": 10}, {"route": "37", "longitude": -122.445407, "d_time": 137, "time": 38580, "latitude": 37.770089, "trip": " 8517", "size": 10}, {"route": "37", "longitude": -122.44578, "d_time": 59, "time": 36960, "latitude": 37.75041, "trip": " 8517", "size": 10}, {"d_time": 59, "time": 37560, "latitude": 37.75041, "route": "37", "trip": " 8517", "longitude": -122.44578, "size": 0}], [{"d_time": 261, "time": 36600, "latitude": 37.767768, "route": "37", "trip": " 8512", "longitude": -122.429088, "size": 0}, {"route": "37", "longitude": -122.429088, "d_time": 261, "time": 36600, "latitude": 37.767768, "trip": " 8512", "size": 10}, {"route": "37", "longitude": -122.435449, "d_time": 188, "time": 36300, "latitude": 37.76246, "trip": " 8512", "size": 10}, {"route": "37", "longitude": -122.4442, "d_time": 14, "time": 35880, "latitude": 37.74715, "trip": " 8512", "size": 10}, {"route": "37", "longitude": -122.445407, "d_time": 373, "time": 37380, "latitude": 37.770089, "trip": " 8512", "size": 10}, {"route": "37", "longitude": -122.44578, "d_time": -8, "time": 35760, "latitude": 37.75041, "trip": " 8512", "size": 10}, {"d_time": -8, "time": 36360, "latitude": 37.75041, "route": "37", "trip": " 8512", "longitude": -122.44578, "size": 0}], [{"d_time": 0, "time": 35400, "latitude": 37.767768, "route": "37", "trip": " 8514", "longitude": -122.429088, "size": 0}, {"route": "37", "longitude": -122.429088, "d_time": 0, "time": 35400, "latitude": 37.767768, "trip": " 8514", "size": 10}, {"route": "37", "longitude": -122.429088, "d_time": 0, "time": 35100, "latitude": 37.767768, "trip": " 8514", "size": 10}, {"route": "37", "longitude": -122.429088, "d_time": 0, "time": 34680, "latitude": 37.767768, "trip": " 8514", "size": 10}, {"route": "37", "longitude": -122.429088, "d_time": 0, "time": 36180, "latitude": 37.767768, "trip": " 8514", "size": 10}, {"route": "37", "longitude": -122.429088, "d_time": 0, "time": 34560, "latitude": 37.767768, "trip": " 8514", "size": 10}, {"route": "37", "longitude": -122.429088, "d_time": 338, "time": 34200, "latitude": 37.767768, "trip": " 8514", "size": 10}, {"route": "37", "longitude": -122.435449, "d_time": 335, "time": 33900, "latitude": 37.76246, "trip": " 8514", "size": 10}, {"route": "37", "longitude": -122.4442, "d_time": 59, "time": 33480, "latitude": 37.74715, "trip": " 8514", "size": 10}, {"route": "37", "longitude": -122.445407, "d_time": 305, "time": 34980, "latitude": 37.770089, "trip": " 8514", "size": 10}, {"route": "37", "longitude": -122.44578, "d_time": -3, "time": 33360, "latitude": 37.75041, "trip": " 8514", "size": 10}, {"d_time": -3, "time": 33960, "latitude": 37.75041, "route": "37", "trip": " 8514", "longitude": -122.44578, "size": 0}], [{"d_time": 325, "time": 33300, "latitude": 37.767768, "route": "37", "trip": " 8517", "longitude": -122.429088, "size": 0}, {"route": "37", "longitude": -122.429088, "d_time": 325, "time": 33300, "latitude": 37.767768, "trip": " 8517", "size": 10}, {"route": "37", "longitude": -122.435449, "d_time": 388, "time": 33000, "latitude": 37.76246, "trip": " 8517", "size": 10}, {"route": "37", "longitude": -122.4442, "d_time": 149, "time": 32580, "latitude": 37.74715, "trip": " 8517", "size": 10}, {"route": "37", "longitude": -122.445407, "d_time": 360, "time": 34080, "latitude": 37.770089, "trip": " 8517", "size": 10}, {"route": "37", "longitude": -122.44578, "d_time": 112, "time": 32460, "latitude": 37.75041, "trip": " 8517", "size": 10}, {"d_time": 112, "time": 33060, "latitude": 37.75041, "route": "37", "trip": " 8517", "longitude": -122.44578, "size": 0}], [{"d_time": 207, "time": 32400, "latitude": 37.767768, "route": "37", "trip": " 8512", "longitude": -122.429088, "size": 0}, {"route": "37", "longitude": -122.429088, "d_time": 207, "time": 32400, "latitude": 37.767768, "trip": " 8512", "size": 10}, {"route": "37", "longitude": -122.435449, "d_time": 292, "time": 32100, "latitude": 37.76246, "trip": " 8512", "size": 10}, {"route": "37", "longitude": -122.4442, "d_time": 49, "time": 31680, "latitude": 37.74715, "trip": " 8512", "size": 10}, {"route": "37", "longitude": -122.445407, "d_time": 278, "time": 33180, "latitude": 37.770089, "trip": " 8512", "size": 10}, {"route": "37", "longitude": -122.44578, "d_time": 8, "time": 31560, "latitude": 37.75041, "trip": " 8512", "size": 10}, {"d_time": 8, "time": 32160, "latitude": 37.75041, "route": "37", "trip": " 8512", "longitude": -122.44578, "size": 0}], [{"d_time": 292, "time": 30600, "latitude": 37.767768, "route": "37", "trip": " 8525", "longitude": -122.429088, "size": 0}, {"route": "37", "longitude": -122.429088, "d_time": 292, "time": 30600, "latitude": 37.767768, "trip": " 8525", "size": 10}, {"route": "37", "longitude": -122.435449, "d_time": 300, "time": 30300, "latitude": 37.76246, "trip": " 8525", "size": 10}, {"route": "37", "longitude": -122.4442, "d_time": 43, "time": 29880, "latitude": 37.74715, "trip": " 8525", "size": 10}, {"route": "37", "longitude": -122.445407, "d_time": 249, "time": 31380, "latitude": 37.770089, "trip": " 8525", "size": 10}, {"route": "37", "longitude": -122.44578, "d_time": 13, "time": 29760, "latitude": 37.75041, "trip": " 8525", "size": 10}, {"d_time": 13, "time": 30360, "latitude": 37.75041, "route": "37", "trip": " 8525", "longitude": -122.44578, "size": 0}], [{"d_time": 122, "time": 29700, "latitude": 37.767768, "route": "37", "trip": " 8514", "longitude": -122.429088, "size": 0}, {"route": "37", "longitude": -122.429088, "d_time": 122, "time": 29700, "latitude": 37.767768, "trip": " 8514", "size": 10}, {"route": "37", "longitude": -122.435449, "d_time": 117, "time": 29400, "latitude": 37.76246, "trip": " 8514", "size": 10}, {"route": "37", "longitude": -122.4442, "d_time": -43, "time": 28980, "latitude": 37.74715, "trip": " 8514", "size": 10}, {"route": "37", "longitude": -122.445407, "d_time": 57, "time": 30480, "latitude": 37.770089, "trip": " 8514", "size": 10}, {"route": "37", "longitude": -122.44578, "d_time": -19, "time": 28860, "latitude": 37.75041, "trip": " 8514", "size": 10}, {"d_time": -19, "time": 29460, "latitude": 37.75041, "route": "37", "trip": " 8514", "longitude": -122.44578, "size": 0}], [{"d_time": 518, "time": 28800, "latitude": 37.767768, "route": "37", "trip": " 8517", "longitude": -122.429088, "size": 0}, {"route": "37", "longitude": -122.429088, "d_time": 518, "time": 28800, "latitude": 37.767768, "trip": " 8517", "size": 10}, {"route": "37", "longitude": -122.435449, "d_time": 386, "time": 28500, "latitude": 37.76246, "trip": " 8517", "size": 10}, {"route": "37", "longitude": -122.4442, "d_time": -25, "time": 28080, "latitude": 37.74715, "trip": " 8517", "size": 10}, {"route": "37", "longitude": -122.445407, "d_time": 750, "time": 29580, "latitude": 37.770089, "trip": " 8517", "size": 10}, {"route": "37", "longitude": -122.44578, "d_time": -12, "time": 27960, "latitude": 37.75041, "trip": " 8517", "size": 10}, {"d_time": -12, "time": 28560, "latitude": 37.75041, "route": "37", "trip": " 8517", "longitude": -122.44578, "size": 0}], [{"d_time": 381, "time": 27900, "latitude": 37.767768, "route": "37", "trip": " 8512", "longitude": -122.429088, "size": 0}, {"route": "37", "longitude": -122.429088, "d_time": 381, "time": 27900, "latitude": 37.767768, "trip": " 8512", "size": 10}, {"route": "37", "longitude": -122.435449, "d_time": 359, "time": 27600, "latitude": 37.76246, "trip": " 8512", "size": 10}, {"route": "37", "longitude": -122.4442, "d_time": 63, "time": 27180, "latitude": 37.74715, "trip": " 8512", "size": 10}, {"route": "37", "longitude": -122.445407, "d_time": 526, "time": 28680, "latitude": 37.770089, "trip": " 8512", "size": 10}, {"route": "37", "longitude": -122.44578, "d_time": 13, "time": 27060, "latitude": 37.75041, "trip": " 8512", "size": 10}, {"d_time": 13, "time": 27660, "latitude": 37.75041, "route": "37", "trip": " 8512", "longitude": -122.44578, "size": 0}], [{"d_time": 108, "time": 26100, "latitude": 37.767768, "route": "37", "trip": " 8525", "longitude": -122.429088, "size": 0}, {"route": "37", "longitude": -122.429088, "d_time": 108, "time": 26100, "latitude": 37.767768, "trip": " 8525", "size": 10}, {"route": "37", "longitude": -122.435449, "d_time": 225, "time": 25800, "latitude": 37.76246, "trip": " 8525", "size": 10}, {"route": "37", "longitude": -122.4442, "d_time": 68, "time": 25380, "latitude": 37.74715, "trip": " 8525", "size": 10}, {"route": "37", "longitude": -122.445407, "d_time": 128, "time": 26880, "latitude": 37.770089, "trip": " 8525", "size": 10}, {"route": "37", "longitude": -122.44578, "d_time": 26, "time": 25260, "latitude": 37.75041, "trip": " 8525", "size": 10}, {"d_time": 26, "time": 25860, "latitude": 37.75041, "route": "37", "trip": " 8525", "longitude": -122.44578, "size": 0}], [{"d_time": 39, "time": 25200, "latitude": 37.767768, "route": "37", "trip": " 8514", "longitude": -122.429088, "size": 0}, {"route": "37", "longitude": -122.429088, "d_time": 39, "time": 25200, "latitude": 37.767768, "trip": " 8514", "size": 10}, {"route": "37", "longitude": -122.435449, "d_time": 37, "time": 24900, "latitude": 37.76246, "trip": " 8514", "size": 10}, {"route": "37", "longitude": -122.4442, "d_time": -21, "time": 24480, "latitude": 37.74715, "trip": " 8514", "size": 10}, {"route": "37", "longitude": -122.445407, "d_time": -19, "time": 25980, "latitude": 37.770089, "trip": " 8514", "size": 10}, {"d_time": -19, "time": 26580, "latitude": 37.770089, "route": "37", "trip": " 8514", "longitude": -122.445407, "size": 0}], [{"d_time": 0, "time": 24360, "latitude": 37.767768, "route": "37", "trip": " 8517", "longitude": -122.429088, "size": 0}, {"route": "37", "longitude": -122.429088, "d_time": 0, "time": 24360, "latitude": 37.767768, "trip": " 8517", "size": 10}, {"route": "37", "longitude": -122.429088, "d_time": 432, "time": 24300, "latitude": 37.767768, "trip": " 8517", "size": 10}, {"route": "37", "longitude": -122.435449, "d_time": 565, "time": 24000, "latitude": 37.76246, "trip": " 8517", "size": 10}, {"route": "37", "longitude": -122.445407, "d_time": 565, "time": 23580, "latitude": 37.770089, "trip": " 8517", "size": 10}, {"route": "37", "longitude": -122.445407, "d_time": 506, "time": 25080, "latitude": 37.770089, "trip": " 8517", "size": 10}, {"d_time": 506, "time": 25680, "latitude": 37.770089, "route": "37", "trip": " 8517", "longitude": -122.445407, "size": 0}], [{"d_time": 0, "time": 23460, "latitude": 37.767768, "route": "37", "trip": " 8512", "longitude": -122.429088, "size": 0}, {"route": "37", "longitude": -122.429088, "d_time": 0, "time": 23460, "latitude": 37.767768, "trip": " 8512", "size": 10}, {"route": "37", "longitude": -122.429088, "d_time": 119, "time": 23400, "latitude": 37.767768, "trip": " 8512", "size": 10}, {"route": "37", "longitude": -122.435449, "d_time": 130, "time": 23100, "latitude": 37.76246, "trip": " 8512", "size": 10}, {"route": "37", "longitude": -122.4442, "d_time": -36, "time": 22680, "latitude": 37.74715, "trip": " 8512", "size": 10}, {"route": "37", "longitude": -122.445407, "d_time": 161, "time": 24180, "latitude": 37.770089, "trip": " 8512", "size": 10}, {"route": "37", "longitude": -122.44578, "d_time": 1, "time": 22560, "latitude": 37.75041, "trip": " 8512", "size": 10}, {"d_time": 1, "time": 23160, "latitude": 37.75041, "route": "37", "trip": " 8512", "longitude": -122.44578, "size": 0}], [{"d_time": 209, "time": 31500, "latitude": 37.767768, "route": "37", "trip": " 8524", "longitude": -122.429088, "size": 0}, {"route": "37", "longitude": -122.429088, "d_time": 209, "time": 31500, "latitude": 37.767768, "trip": " 8524", "size": 10}, {"route": "37", "longitude": -122.435449, "d_time": 226, "time": 31200, "latitude": 37.76246, "trip": " 8524", "size": 10}, {"route": "37", "longitude": -122.4442, "d_time": -40, "time": 30780, "latitude": 37.74715, "trip": " 8524", "size": 10}, {"route": "37", "longitude": -122.445407, "d_time": 238, "time": 32280, "latitude": 37.770089, "trip": " 8524", "size": 10}, {"route": "37", "longitude": -122.44578, "d_time": -11, "time": 30660, "latitude": 37.75041, "trip": " 8524", "size": 10}, {"d_time": -11, "time": 31260, "latitude": 37.75041, "route": "37", "trip": " 8524", "longitude": -122.44578, "size": 0}], [{"d_time": 209, "time": 27000, "latitude": 37.767768, "route": "37", "trip": " 8524", "longitude": -122.429088, "size": 0}, {"route": "37", "longitude": -122.429088, "d_time": 209, "time": 27000, "latitude": 37.767768, "trip": " 8524", "size": 10}, {"route": "37", "longitude": -122.435449, "d_time": 204, "time": 26700, "latitude": 37.76246, "trip": " 8524", "size": 10}, {"route": "37", "longitude": -122.4442, "d_time": 81, "time": 26280, "latitude": 37.74715, "trip": " 8524", "size": 10}, {"route": "37", "longitude": -122.445407, "d_time": 291, "time": 27780, "latitude": 37.770089, "trip": " 8524", "size": 10}, {"route": "37", "longitude": -122.44578, "d_time": 36, "time": 26160, "latitude": 37.75041, "trip": " 8524", "size": 10}, {"d_time": 36, "time": 26760, "latitude": 37.75041, "route": "37", "trip": " 8524", "longitude": -122.44578, "size": 0}], [{"d_time": -23, "time": 22620, "latitude": 37.767768, "route": "37", "trip": " 8524", "longitude": -122.429088, "size": 0}, {"route": "37", "longitude": -122.429088, "d_time": -23, "time": 22620, "latitude": 37.767768, "trip": " 8524", "size": 10}, {"route": "37", "longitude": -122.445407, "d_time": -46, "time": 23400, "latitude": 37.770089, "trip": " 8524", "size": 10}, {"d_time": -46, "time": 24000, "latitude": 37.770089, "route": "37", "trip": " 8524", "longitude": -122.445407, "size": 0}], [{"d_time": 496, "time": 67680, "latitude": 37.767768, "route": "37", "trip": " 8514", "longitude": -122.429088, "size": 0}, {"route": "37", "longitude": -122.429088, "d_time": 496, "time": 67680, "latitude": 37.767768, "trip": " 8514", "size": 10}, {"route": "37", "longitude": -122.435449, "d_time": 313, "time": 67440, "latitude": 37.76246, "trip": " 8514", "size": 10}, {"route": "37", "longitude": -122.4442, "d_time": 42, "time": 67080, "latitude": 37.74715, "trip": " 8514", "size": 10}, {"route": "37", "longitude": -122.445407, "d_time": 687, "time": 68460, "latitude": 37.770089, "trip": " 8514", "size": 10}, {"route": "37", "longitude": -122.44578, "d_time": 19, "time": 66960, "latitude": 37.75041, "trip": " 8514", "size": 10}, {"d_time": 19, "time": 67560, "latitude": 37.75041, "route": "37", "trip": " 8514", "longitude": -122.44578, "size": 0}]]